Workbook

Sheet default_1
A1: Author Full Names | B1: Journal ISO Abbreviation | C1: Publication Date | D1: Publication Year | E1: Cites | F1: DOI | G1: ID | H1: Transport mode | I1: Multimodal components | J1: Total number transactions | K1: Days | L1: Year(s) | M1: Study Area | N1: Structure | O1: Only dataset | P1: Main dataset | Q1: Supplementary datasets | R1: Data accessibility | S1: Analytical category | T1: Analytical subcategory | U1: Techniques | V1: Methods | W1: Derived | X1: Derived from | Y1: Preprocessed | Z1: Features | AA1: Validation metrics | AB1: Tools | AC1: Domain
A2: Rodrigues, Filipe; Borysov, Stanislav S.; Ribeiro, Bernardete; Pereira, Francisco C. | B2: IEEE Trans. Pattern Anal. Mach. Intell. | C2: NOV | D2: 2017 | E2: =VLOOKUP(default_1!F118,Hoja1!$AD$1:$AE$176,2,FALSE) -> 48 | F2: 10.1109/TPAMI.2016.2635136 | G2: P001 | H2: Subway | J2: 2700000 | K2: 151 | L2: 2012-2013 | M2: Singapore | N2: Closed | O2: 0 | P2: 0 | Q2: Events | R2: 0 | S2: Demand forecasting | T2: Spatio-temporal | U2: Bayesian Additive Model-Gaussian Process;LDA | V2: Probability techniques;Natural language processing | W2: 1 | X2: Bayesian additive model; Gaussian process | Y2: 1 | AA2: RAE;Correlation coefficient;R² | AB2: Julia | AC2: Transportation
A3: Tang, Liyang; Zhao, Yang; Tsui, Kwok Leung; He, Yuxin; Pan, Liwei | B3: Appl. Sci.-Basel | C3: AUG | D3: 2020 | E3: =VLOOKUP(default_1!F71,Hoja1!$AD$1:$AE$176,2,FALSE) -> 6 | F3: 10.3390/app10165606 | G3: P002 | H3: Subway | J3: 330000000 | K3: 122 | L3: 2013 | M3: Shenzhen, China | N3: Closed | O3: 0 | P3: 1 | Q3: Regulation;POI;Social/Demographic/Economic | R3: 0 | S3: Classification | T3: Spatio-temporal | U3: k-means;ProClus;HDDC;Cluster refinement framework with Cluster Member Based Stability;PCA | V3: Clustering;Clustering;Clustering;Clustering;Dimensionality reduction | W3: 0 | Y3: 1 | Z3: SFD | AA3: Moran's I;Lagrange multiplier test | AB3: R | AC3: Urban planning
A4: Zhang, Yang; Cheng, Tao | B4: IEEE Trans. Intell. Transp. Syst. | C4: FEB | D4: 2020 | E4: =VLOOKUP(default_1!F86,Hoja1!$AD$1:$AE$176,2,FALSE) -> 2 | F4: 10.1109/TITS.2019.2896460 | G4: P003 | H4: Multimodal | I4: Bus;Subway | J4: 2720000 | L4: 2013 | M4: London, UK | N4: Open-Closed | O4: 0 | P4: 0 | Q4: Survey | R4: 0 | S4: Classification | T4: Social/Economic/Demographic | U4: Thresholding Multi-Channel Convolutional Neural Network | V4: Deep learning | W4: 0 | Y4: 1 | AA4: PPV;TPR;F-Score | AB4: R | AC4: Socio-economic / demographic
A5: Hosoe, Mio; Kuwano, Masashi; Moriyama, Taku | B5: J. Big Data | C5: JAN 7 | D5: 2021 | E5: =VLOOKUP(default_1!F57,Hoja1!$AD$1:$AE$176,2,FALSE) -> 23 | F5: 10.1186/s40537-020-00402-w | G5: P004 | H5: Train | J5: 9008709 | K5: 455 | L5: 2013-2015 | M5: Kagawa Prefecture, Japan | N5: Closed | O5: 1 | P5: 1 | R5: 0 | S5: Pattern analysis | T5: Passenger | U5: Data polishing | V5: Clustering | W5: 1 | X5: Uno et al. 2016 | Y5: 0 | AA5: Thresholds | AC5: Transportation
A6: Le-Minh Kieu; Bhaskar, Ashish; Chung, Edward | B6: Transp. Res. Pt. C-Emerg. Technol. | C6: SEP | D6: 2015 | E6: =VLOOKUP(default_1!F134,Hoja1!$AD$1:$AE$176,2,FALSE) -> 2 | F6: 10.1016/j.trc.2015.03.033 | G6: P005 | H6: Multimodal | I6: Bus;Train;Ferry | J6: 34800000 | K6: 122 | L6: 2012 | M6: South East Queensland, Australia | N6: Closed | O6: 1 | P6: 1 | R6: 0 | S6: Classification | T6: Spatio-temporal | U6: WS-DBSCAN | V6: Clustering | W6: 1 | X6: DBSCAN | Y6: 0 | AA6: Performance | AC6: Transportation
A7: Wang, Wenjing; Wang, Yihong; Correia, Goncalo Homem de Almeida; Chen, Yusen | B7: J. Adv. Transp. | C7: DEC 7 | D7: 2020 | E7: =VLOOKUP(default_1!F64,Hoja1!$AD$1:$AE$176,2,FALSE) -> 14 | F7: 10.1155/2020/6659931 | G7: P006 | H7: Multimodal | I7: Bus;Subway | J7: 120000000 | K7: 8 | L7: 2017 | M7: Beijing, China | N7: Closed | O7: 0 | P7: 0 | Q7: Network;POI | R7: 0 | S7: Passengers flow | T7: Transfer | U7: Gravity-based model;Regression model | V7: Gravity-based model;Regression | W7: 0 | Y7: 1 | Z7: Transfer flow, transfer accesability, transfer time, bus stops per metro station, bus lines per bus stop | AA7: R²;F-Score | AC7: Transportation
A8: Shalit, Nadav; Fire, Michael; Ben-Elia, Eran | B8: Public Transport | C8: JUN | D8: 2023 | E8: =VLOOKUP(default_1!F40,Hoja1!$AD$1:$AE$176,2,FALSE) -> 4 | F8: 10.1007/s12469-022-00309-0 | G8: P007 | H8: Multimodal | I8: Bus;Train | J8: 1000000 | K8: 30 | L8: 2018 | M8: Beer Sheva, Israel;Kiryat Gat, Israel | N8: Open-Closed | O8: 0 | P8: 0 | Q8: Transit Feed;Layers | R8: 0 | S8: Data preprocessing | T8: Data imputation | U8: SHAP;Random Forest;Logistic Regression;XGBoost | V8: Game theory;Classification;Classification;Classification | W8: 0 | Y8: 1 | Z8: Addresses_average;Street_light_average;Traffic_Lights_average;Number_of_points;Average_distance_per_stop;Average_time_per_stop;Average_points_to_stops;Time_diff_of_trip;Time_from_boarding_to_last_stop;Time_from_departure_to_boarding;Predicted_sequence;Hourly_expected_lateness;Boardingtime_Seconds_from_midnight;Boardingtime_weekday;Is_weekend | AA8: Accuracy;TPR;PPV;F-Score;AUC;RMSE;Shapely values | AC8: Transportation
A9: Shin, Yonggeun; Kim, Dong-Kyu; Kim, Eui-Jin | B9: J. Transp. Geogr. | C9: DEC | D9: 2022 | E9: =VLOOKUP(default_1!F7,Hoja1!$AD$1:$AE$176,2,FALSE) -> 13 | F9: 10.1016/j.jtrangeo.2022.103459 | G9: P008 | H9: Multimodal | I9: Bus;Subway | J9: 80000000 | K9: 4 | L9: 2017 | M9: Seoul, South Korea | N9: Open-Closed | O9: 0 | P9: 0 | Q9: Land use | R9: 0 | S9: Classification | T9: Spatio-temporal | U9: Hidden Markov Model;k-means | V9: Stochastic modeling;Clustering | W9: 0 | Y9: 1 | Z9: activity sequence | AA9: AIC;BIC | AC9: Urban planning
A10: Lee, Haengju; Eun, Yongsoon | B10: IEEE Trans. Intell. Transp. Syst. | C10: DEC | D10: 2022 | E10: =VLOOKUP(default_1!F9,Hoja1!$AD$1:$AE$176,2,FALSE) -> 2 | F10: 10.1109/TITS.2022.3203705 | G10: P010 | H10: Subway | J10: 9663319 | K10: 30 | L10: 2018 | M10: Daegu, South Korea | N10: Closed | O10: 0 | P10: 1 | Q10: Layers | R10: 0 | S10: Demand forecasting | T10: Marketing | U10: Linear programming;Dynamic programming;Poisson distribution | V10: Optimization;Optimization;Clustering | W10: 0 | Y10: 1 | AA10: Performance | AC10: Marketing
A11: Liyanage, Sohani; Abduljabbar, Rusul; Dia, Hussein; Tsai, Pei -Wei | B11: J. Urban Manag. | C11: SEP | D11: 2022 | E11: =VLOOKUP(default_1!F13,Hoja1!$AD$1:$AE$176,2,FALSE) -> 11 | F11: 10.1016/j.jum.2022.05.002 | G11: P011 | H11: Bus | J11: 715375 | K11: 31 | L11: 2018 | M11: Melbourne, Australia | N11: Closed | O11: 1 | P11: 1 | R11: 0 | S11: Demand forecasting | T11: Spatio-temporal | U11: Long short-term memory;Bidirectional Long short-term memory;Unidirectional Long short-term memory | V11: Deep learning;Deep learning;Deep learning | W11: 0 | Y11: 1 | AA11: MAPE;MAE;RMSE;R² | AB11: Matlab | AC11: Transportation
A12: Wang, Xueqin; Xu, Xinyue; Wu, Yuankai; Liu, Jun | B12: Soft Comput. | C12: JUN | D12: 2022 | E12: =VLOOKUP(default_1!F23,Hoja1!$AD$1:$AE$176,2,FALSE) -> 14 | F12: 10.1007/s00500-022-07025-8 | G12: P012 | H12: Subway | K12: 73 | L12: 2019 | M12: Beijing, China | N12: Closed | O12: 1 | P12: 1 | R12: 0 | S12: Demand forecasting | T12: Flow | U12: STGGA | V12: Deep learning | W12: 1 | X12: GCN;GRU | Y12: 1 | AA12: RMSE;accuracy;R²;Friedman test;Wilcoxon signed-rank test | AB12: TensorFlow | AC12: Transportation
A13: Lin, Pengfei; Weng, Jiancheng; Brands, Devi K.; Qian, Huimin; Yin, Baocai | B13: IET Intell. Transp. Syst. | C13: DEC 27 | D13: 2020 | E13: =VLOOKUP(default_1!F61,Hoja1!$AD$1:$AE$176,2,FALSE) -> 2 | F13: 10.1049/iet-its.2020.0469 | G13: P013 | H13: Multimodal | I13: Bus;Subway | J13: 3650000000 | K13: 365 | L13: 2018-2019 | M13: Beijing, China | N13: Closed | O13: 0 | P13: 0 | Q13: Meteorological;POI;Network;Land use;Layers | R13: 0 | S13: Pattern analysis | T13: Meteorological | U13: LightGBM | V13: Regression | W13: 0 | Y13: 0 | Z13: average temperature;relative humidity;average wind speed;rainfall;AQI;snowfall;month;weekend/public holiday;residence;office;distance from CBD;education;commercial;hospital;bus;land use mix;subway;scenic spot;transport hub | AA13: R²;MAE;RMSE;Running time | AC13: Transportation
A14: Sun, Feng; Su, Wenheng; Liu, Weixuan; Cao, Hui; Guo, Dong; Zhu, Ye | B14: J. Electr. Comput. Eng. | D14: 2018 | E14: =VLOOKUP(default_1!F115,Hoja1!$AD$1:$AE$176,2,FALSE) -> 1 | F14: 10.1155/2018/2975615 | G14: P014 | H14: Bus | J14: 10658558 | K14: 7 | L14: 2017 | M14: Qingdao, China | N14: Open | O14: 1 | P14: 1 | R14: 0 | S14: Demand forecasting | T14: Spatio-temporal | U14: ARIMA;NARX | V14: Time series analysis;Time series analysis | W14: 0 | Y14: 1 | AA14: Wilcoxon signed-rank test;acuracy;MSE;R;Relative error | AB14: Matlab;SQL | AC14: Transportation
A15: Briand, Anne-Sarah; Come, Etienne; Trepanier, Martin; Oukhellou, Latifa | B15: Transp. Res. Pt. C-Emerg. Technol. | C15: JUN | D15: 2017 | E15: =VLOOKUP(default_1!F120,Hoja1!$AD$1:$AE$176,2,FALSE) -> 2 | F15: 10.1016/j.trc.2017.03.021 | G15: P015 | H15: Bus | J15: 3492310 | K15: 140 | L15: 2005-2009 | M15: Gatineau, Canada | N15: Open | O15: 1 | P15: 1 | R15: 0 | S15: Classification | T15: Spatio-temporal | U15: Gaussian mixture models | V15: Classification | W15: 0 | Y15: 0 | Z15: KL divergence;entropy | AA15: ICL;Entropy | AC15: Transportation
A16: Tonnelier, E.; Baskiotis, N.; Guigue, V.; Gallinari, P. | B16: Neurocomputing | C16: JUL 12 | D16: 2018 | E16: =VLOOKUP(default_1!F33,Hoja1!$AD$1:$AE$176,2,FALSE) -> 0 | F16: 10.1016/j.neucom.2017.12.067 | G16: P016 | H16: Subway | J16: 256000000 | K16: 91 | L16: 2015 | M16: Paris, France | N16: Closed | O16: 0 | P16: 1 | Q16: Network Status Updates | R16: 0 | S16: Anomaly detection | T16: Service disruptions/incidents | U16: Anomaly detection;Non-negative matrix factorization;Continuous user-based model | V16: Anomaly detection;Dimensionality reduction;Anomaly detection | W16: 0 | Y16: 0 | AA16: Std deviation;ROC curve;Accuracy;PPV | AC16: Transportation
A17: Yu, Wei; Bai, Hua; Chen, Jun; Yan, Xingchen | B17: IEEE Access | D17: 2019 | E17: =VLOOKUP(default_1!F29,Hoja1!$AD$1:$AE$176,2,FALSE) -> 4 | F17: 10.1109/ACCESS.2019.2943598 | G17: P017 | H17: Subway | J17: 1197147 | K17: 1 | L17: 2017 | M17: Nanjing, China | N17: Closed | O17: 1 | P17: 1 | R17: 0 | S17: Anomaly detection | T17: Passengers behaviour | U17: OD analysis | V17: OD matrix | W17: 0 | Y17: 1 | Z17: Inbound if next day;negative time taken;over 300 minutes;In and out same sattion in 0-3 minutes;In and out same station in 4-300 minutes;In and out same sation;swiping card over 8 times | AC17: Transportation
A18: Kapuku, Christian; Kho, Seung-Young; Kim, Dong-Kyu; Cho, Shin-Hyung | B18: Transp. Res. Record | C18: NOV | D18: 2021 | E18: =VLOOKUP(default_1!F38,Hoja1!$AD$1:$AE$176,2,FALSE) -> 4 | F18: 10.1177/03611981211045071 | G18: P018 | H18: Multimodal | I18: Subway;Bus | J18: 120400 | K18: 790 | L18: 2016-2018 | M18: Seoul, South Korea | N18: Closed | O18: 1 | P18: 1 | Q18: Travel data;Network | R18: 0 | S18: Performance indicators | T18: Mobility performance | U18: k-NN;Logistic regression;Support vector machine;Decision tree;Random forest;ReliefF | V18: Classification;Classification;Classification;Classification;Classification;Feature selection | W18: 0 | Y18: 1 | Z18: indicator bike-sharing travel time < Bus travel time;Bus trip travel time;Bus trip boarding time;Bus trip travel speed;Bus trip travel distance;Bike user’s gender;Bike user’s age;Bus detour factor: Bike travel distance - Bus traveldistance;The difference in travel speeds between bike-sharing and bus;Bike-sharing trip travel distance;Bike-sharing trip speed;The portion of the bike lane in the route;Total travel time for bike–transit intermodal trips;Total travel time for bus–transit intermodal trips | AA18: t-Value;Wilcoxon signed-rank test;TPR;TNR;PPV;FDR;FPR;AUC | AC18: Transportation
A19: Yen, Barbara T. H.; Mulley, Corinne; Tseng, Wen-Chun; Chiou, Yu-Chiun | B19: Case Stud. Transp. Policy | C19: SEP | D19: 2018 | E19: =VLOOKUP(default_1!F108,Hoja1!$AD$1:$AE$176,2,FALSE) -> 45 | F19: 10.1016/j.cstp.2018.01.005 | G19: P019 | H19: Multimodal | I19: Bus;Train;Ferry;Tram | J19: 15000000 | K19: 31 | L19: 2013 | M19: South East Queensland, Australia | N19: Closed | O19: 0 | P19: 1 | Q19: Social/Demographic/Economic;Layers | R19: 0 | S19: Performance indicators | T19: Transfer | U19: Latent class nested logit | V19: Classification | W19: 0 | Y19: 0 | Z19: Travel time;Travel cost;Travel zone;9 journey trip;Peak hour trip;Weekday trip;Commuter trip;Feeder bus stop density_ Heavy rail;Population density;Age (>65 years old);Students (>four years old);Employment;Public transport as main travel mode;Car number (more than two);High income (>1500/pw) | AA19: BIC;AIC;log likelihood ratios;number of parameters | AC19: Transportation
A20: Lee, Hasik; Park, Ho-Chul; Kho, Seung-Young; Kim, Dong-Kyu | B20: J. Transp. Geogr. | C20: OCT | D20: 2019 | E20: =VLOOKUP(default_1!F89,Hoja1!$AD$1:$AE$176,2,FALSE) -> 2 | F20: 10.1016/j.jtrangeo.2019.102546 | G20: P020 | H20: Multimodal | I20: Bus;Subway;Train | J20: 108311249 | K20: 7 | L20: 2017 | M20: Seoul, South Korea | N20: Closed | O20: 0 | P20: 0 | Q20: Social/Demographic/Economic;Land use;Transit Feed | R20: 0 | S20: Performance indicators | T20: Multimodal | U20: Transit competitiveness index | V20: Authors technique | W20: 0 | Y20: 1 | Z20: Transit competitiveness index | AA20: Correlation coefficient | AB20: QGIS | AC20: Transportation
A21: Hamedmoghadam, Homayoun; Vu, Hai L.; Jalili, Mahdi; Saberi, Meead; Stone, Lewi; Hoogendoorn, Serge | B21: Transp. Res. Pt. C-Emerg. Technol. | C21: AUG | D21: 2021 | E21: =VLOOKUP(default_1!F47,Hoja1!$AD$1:$AE$176,2,FALSE) -> 5 | F21: 10.1016/j.trc.2021.103210 | G21: P021 | H21: Multimodal | I21: Train;Tram;Bus | J21: 107576000 | K21: 61 | L21: 2017 | M21: Melbourne, Australia | N21: Closed | O21: 1 | P21: 1 | R21: 0 | S21: Origin-Destination | T21: OD Matrix Generation | U21: OD matrix;Random forest;Binary classification | V21: OD matrix;Classification;Classification | W21: 0 | Y21: 1 | Z21: ITT | AA21: Accuracy;Performance | AC21: Transportation
A22: Guzman, Luis A.; Beltran, Carlos; Bonilla, Jorge; Cardona, Santiago Gomez | B22: Transp. Res. Pt. A-Policy Pract. | C22: AUG | D22: 2021 | E22: =VLOOKUP(default_1!F45,Hoja1!$AD$1:$AE$176,2,FALSE) -> 7 | F22: 10.1016/j.tra.2021.06.018 | G22: P022 | H22: Bus | J22: 9300000 | K22: 3012 | L22: 2010-1018 | M22: Bogotá, Colombia | N22: Open | O22: 0 | P22: 0 | Q22: Travel data;Social/Demographic/Economic;Travel data;Social/Demographic/Economic | R22: 0 | S22: Performance indicators | T22: Fare | U22: Panel data model;Partitioning around medoids | V22: Panel analysis;Clustering | W22: 0 | Y22: 0 | AA22: t-Value | AB22: R | AC22: Transportation
A23: Rahbar, Mohadeseh; Hickman, Mark; Mesbah, Mahmoud; Tavassoli, Ahmad | B23: IEEE Trans. Intell. Transp. Syst. | C23: APR | D23: 2019 | E23: =VLOOKUP(default_1!F97,Hoja1!$AD$1:$AE$176,2,FALSE) -> 12 | F23: 10.1109/TITS.2018.2852726 | G23: P023 | H23: Multimodal | I23: Bus;Ferry;Train | J23: 189963 | K23: 31 | L23: 2013 | M23: South East Queensland, Australia | N23: Closed | O23: 0 | P23: 1 | Q23: Transit Feed;Meteorological;Network | R23: 0 | S23: Path planning/finding | T23: Route choice | U23: Bayesian Hierarchical;Markov chain Monte Carlo;Multinomial Logit | V23: Probability techniques;Probability techniques;Regression | W23: 0 | Y23: 1 | AA23: BIC;RMSE | AB23: R;JAGS | AC23: Transportation
A24: Zhu, Wei; Fan, Wei-li; Wahaballa, Amr M.; Wei, Jin | B24: Transportation | C24: DEC | D24: 2020 | E24: =VLOOKUP(default_1!F66,Hoja1!$AD$1:$AE$176,2,FALSE) -> 7 | F24: 10.1007/s11116-019-10040-8 | G24: P024 | H24: Train | J24: 44080649 | K24: 7 | L24: 2016 | M24: Beijing, China | N24: Closed | O24: 1 | P24: 1 | R24: 0 | S24: Path planning/finding | T24: Route choice | U24: Local outlier factor;Rodriguez–Laio 2014 | V24: Anomaly detection;Clustering | W24: 0 | Y24: 1 | Z24: OD absolute threshold;OD relative threshold;fastest travel time;slowest travel time | AA24: Thresholds | AC24: Transportation
A25: Zhang, Nan; Jia, Wei; Wang, Peihua; Dung, Chung-Hin; Zhao, Pengcheng; Leung, Kathy; Su, Boni; Cheng, Reynold; Li, Yuguo | B25: Cities | C25: MAY | D25: 2021 | E25: =VLOOKUP(default_1!F55,Hoja1!$AD$1:$AE$176,2,FALSE) -> 5 | F25: 10.1016/j.cities.2021.103139 | G25: P025 | H25: Train | J25: 272000000 | K25: 91 | L25: 2020 | M25: Hong Kong, China | N25: Closed | O25: 0 | P25: 0 | Q25: Social/Demographic/Economic;COVID-19;COVID-19;Population mobility;Regulation;Network;Travel data | R25: 0 | S25: Pattern analysis | T25: COVID-19 | U25: Descriptive statistics | V25: Descriptive statistics | W25: 0 | Y25: 1 | AA25: Correlation coefficient | AC25: Public health
A26: Rodriguez Gonzalez, Ana Belen; Wilby, Mark R.; Vinagre Diaz, Juan Jose; Fernandez Pozo, Ruben | B26: Sensors | C26: OCT | D26: 2021 | E26: =VLOOKUP(default_1!F37,Hoja1!$AD$1:$AE$176,2,FALSE) -> 13 | F26: 10.3390/s21196574 | G26: P026 | H26: Multimodal | I26: Subway;Train;Bus | J26: 5825614 | K26: 234 | L26: 2020 | M26: Fuenlabrada, Spain | N26: Open | O26: 0 | P26: 0 | Q26: Sensor data | R26: 0 | S26: Pattern analysis | T26: COVID-19 | U26: Regression Trees;Gaussian Process Regressor | V26: Regression;Regression | W26: 0 | Y26: 1 | AA26: MAPE | AB26: Matlab | AC26: Public health
A27: Qiu, Guo; Song, Rui; He, Shiwei; Xu, Wangtu; Jiang, Min | B27: IEEE Trans. Intell. Transp. Syst. | C27: SEP | D27: 2019 | E27: =VLOOKUP(default_1!F90,Hoja1!$AD$1:$AE$176,2,FALSE) -> 12 | F27: 10.1109/TITS.2018.2875466 | G27: P027 | H27: Bus | J27: 40000000 | K27: 5 | L27: 2015 | M27: Beijing, China | N27: Closed | O27: 1 | P27: 1 | R27: 0 | S27: Path planning/finding | T27: Custom routes | U27: P-DN;DBSCAN;k-means;Gaussian mixture models | V27: Clustering;Clustering;Clustering;Clustering | W27: 1 | X27: DBSCAN | Y27: 1 | AA27: CP;SP;DBI;DI;ARI;AMI | AB27: Matlab | AC27: Transportation
A28: El Mahrsi, Mohamed K.; Come, Etienne; Oukhellou, Latifa; Verleysen, Michel | B28: IEEE Trans. Intell. Transp. Syst. | C28: MAR | D28: 2017 | E28: =VLOOKUP(default_1!F122,Hoja1!$AD$1:$AE$176,2,FALSE) -> 0 | F28: 10.1109/TITS.2016.2600515 | G28: P028 | H28: Bus | J28: 5404096 | K28: 30 | L28: 2014 | M28: Rennes, France | N28: Open | O28: 1 | P28: 1 | R28: 0 | S28: Classification | T28: Spatio-temporal | U28: Poisson mixture;Mixture of unigrams model | V28: Clustering;Clustering | W28: 1 | X28: Count series clustering (Come and Oukhellou 2014) | Y28: 1 | AA28: log likelihood ratios;AIC;BIC | AC28: Transportation
A29: Ye, Pengyao; Ma, Yiqing | B29: Transp. Res. Record | C29: FEB | D29: 2023 | E29: =VLOOKUP(default_1!F14,Hoja1!$AD$1:$AE$176,2,FALSE) -> 2 | F29: 10.1177/03611981221111355 | G29: P029 | H29: Bus | J29: 96065229 | K29: 31 | L29: 2019 | M29: Chengdu, China | N29: Open | O29: 0 | P29: 1 | Q29: Layers | R29: 0 | S29: Pattern analysis | T29: Passenger | U29: Logistic regression;n-gram;DBSCAN | V29: Regression;Natural language processing;Clustering | W29: 1 | X29: n-gram (Zhao et al. 2018) | Y29: 1 | AA29: Accuracy | AC29: Transportation
A30: Zhao, Pengjun; Cao, Yushu | B30: Transp. Policy | C30: JUN | D30: 2020 | E30: =VLOOKUP(default_1!F76,Hoja1!$AD$1:$AE$176,2,FALSE) -> 20 | F30: 10.1016/j.tranpol.2020.03.006 | G30: P030 | H30: Subway | J30: 81763455 | K30: 7 | L30: 2015 | M30: Shanghai, China | N30: Closed | O30: 0 | P30: 0 | Q30: Social/Demographic/Economic | R30: 0 | S30: Pattern analysis | T30: Social/Economic/Demographic | U30: GWR;Ordinary least squares;k-means | V30: Regression;Regression;Clustering | W30: 1 | X30: Long and Thill 2015, Alexander et al. 2015 | Y30: 1 | AA30: VIF;Moran's I;R²;AIC;Correlation coefficient;t-Value;AIC | AB30: SQL | AC30: Socio-economic / demographic
A31: Cheng, Long; Huang, Jie; Jin, Tanhua; Chen, Wendong; Li, Aoyong; Witlox, Frank | B31: J. Transp. Geogr. | C31: FEB | D31: 2023 | E31: =VLOOKUP(default_1!F4,Hoja1!$AD$1:$AE$176,2,FALSE) -> 20 | F31: 10.1016/j.jtrangeo.2023.103545 | G31: P031 | H31: Bike | J31: 19720000 | K31: 30 | L31: 2017 | M31: Nanjing, China | N31: Closed | O31: 0 | P31: 0 | Q31: Social/Demographic/Economic;Social/Demographic/Economic;Layers;Layers;Land use;Layers;Network;Meteorological | R31: 0 | S31: Pattern analysis | T31: Multimodal | U31: Generalised additive mixed model | V31: Regression | W31: 0 | Y31: 0 | Z31: SBBS-metro integrated use, FFBS-metro integrated use, Population density, Employment density, Street connectivity, Road density, Land use mix3, Distance to CBD, Number of feeder bus lines, Rainfall, Temperature, Time of day, Day of week | AA31: estimated degree of freedom;R²;confidence intervals | AC31: Transportation
A32: Ji, Yanjie; Ma, Xinwei; He, Mingjia; Jin, Yuchuan; Yuan, Yufei | B32: J. Clean Prod. | C32: MAY 10 | D32: 2020 | E32: =VLOOKUP(default_1!F77,Hoja1!$AD$1:$AE$176,2,FALSE) -> 38 | F32: 10.1016/j.jclepro.2020.120110 | G32: P032 | H32: Bike | J32: 3233566 | K32: 7 | L32: 2017 | M32: Nanjing, China | N32: Closed | O32: 0 | P32: 0 | Q32: Land use | R32: 0 | S32: Performance indicators | T32: Mobility performance | U32: Ortegatong et al. 2013;Binary logistic model | V32: Classification;Regression | W32: 0 | Y32: 0 | Z32: User type;Riding distance;Riding time;Trips during morning peak hours;Trips during afternoon peak hours;Trips during off-peak hours;Trips on workdays;Trips on weekends;Working POI;Residential POI;Transit POI;Entertainment POI;Other POIs;Distance to CBD | AA32: VIF;pseudo-R² | AC32: Transportation
A33: Peng, Liqiang; Li, Qiang; Wang, Fei | B33: Multimedia Syst. | C33: APR | D33: 2023 | E33: =VLOOKUP(default_1!F17,Hoja1!$AD$1:$AE$176,2,FALSE) -> 13 | F33: 10.1007/s00530-022-00967-x | G33: P033 | H33: Multimodal | I33: Bus;Subway | J33: 30000000 | K33: 7 | M33: Singapore | N33: Closed | O33: 0 | P33: 0 | Q33: POI | R33: 0 | S33: Classification | T33: Social/Economic/Demographic | U33: Ranking Algorithm;Top-k neighbor;TF-IDF;LDA | V33: Ranking algorithm;Regression;Natural language processing;Natural language processing | W33: 0 | X33: PageRank (Page and Brin 1998) | Y33: 1 | AA33: Accuracy | AC33: Transportation
A34: Rodriguez Gonzalez, Ana Belen; Vinagre Diaz, Juan Jose; Wilby, Mark R.; Fernandez Pozo, Ruben | B34: Sensors | C34: JAN | D34: 2022 | E34: =VLOOKUP(default_1!F31,Hoja1!$AD$1:$AE$176,2,FALSE) -> 31 | F34: 10.3390/s22010017 | G34: P034 | H34: Multimodal | I34: Bus;Train;Tram;Subway | J34: 500000000 | K34: 120 | L34: 2018-2019 | M34: Madrid, Spain | N34: Closed | O34: 0 | P34: 1 | Q34: Network | R34: 0 | S34: Performance indicators | T34: Journey time | U34: OD matrix | V34: OD matrix | W34: 0 | Y34: 0 | AC34: Transportation
A35: Wang, Yun; Currim, Faiz; Ram, Sudha | B35: Inf. Syst. Res. | C35: JUN | D35: 2022 | E35: =VLOOKUP(default_1!F27,Hoja1!$AD$1:$AE$176,2,FALSE) -> 52 | F35: 10.1287/isre.2021.1072 | G35: P035 | H35: Bus | J35: 210000000 | K35: 214 | L35: 2014 | M35: Fortaleza, Brazil | N35: Open | O35: 0 | P35: 0 | Q35: POI;Meteorological | R35: 0 | S35: Pattern analysis | T35: Spatio-temporal | U35: Deep Learning of Spatiotemporal Patterns | V35: Deep learning | W35: 0 | X35: CNN;LSTM;NE;FNN | Y35: 1 | AA35: MAE;RMSE;SMAPE;Wilcoxon rank-sum test | AC35: Transportation
A36: Maeda, Takashi Nicholas; Shiode, Narushige; Zhong, Chen; Mori, Junichiro; Sakimoto, Tetsuo | B36: J. Big Data | C36: JAN 14 | D36: 2019 | E36: =VLOOKUP(default_1!F101,Hoja1!$AD$1:$AE$176,2,FALSE) -> 28 | F36: 10.1186/s40537-019-0168-5 | G36: P036 | H36: Train | J36: 1808915180 | K36: 730 | L36: 2013-2015 | M36: Kansai Area, Japan | N36: Closed | O36: 1 | P36: 1 | R36: 0 | S36: Pattern analysis | T36: Activity detection | U36: Extraction of Activity Types and Change Detection;Non-negative matrix factorization;Jensen-Shannon divergence | V36: Authors technique;Dimensionality reduction;Probability techniques | W36: 1 | X36: Fan et al. 2014 | Y36: 1 | AA36: Correlation coefficient | AC36: Urban planning
A37: Du, Bowen; Liu, Chuanren; Zhou, Wenjun; Hou, Zhenshan; Xiong, Hui | B37: IEEE Trans. Knowl. Data Eng. | C37: MAR 1 | D37: 2019 | E37: =VLOOKUP(default_1!F98,Hoja1!$AD$1:$AE$176,2,FALSE) -> 102 | F37: 10.1109/TKDE.2018.2834909 | G37: P037 | H37: Multimodal | I37: Bus;Subway | J37: 1700000000 | K37: 91 | L37: 2014 | M37: Beijing, China | N37: Closed | O37: 0 | P37: 0 | Q37: POI;Network Status Updates | R37: 0 | S37: Anomaly detection | T37: Passengers behaviour | U37: Suspect identification models;DBSCAN | V37: Authors technique;Clustering | W37: 0 | Y37: 0 | Z37: Travel Time;Frequency;Short-Distance Rides;Transitions among Functional Zones;Frequently Visited Regions;Deviation from the Social Norm;Historical Behaviours | AA37: PPV;TPR;F-Score | AB37: Java;Scala;Apache Spark | AC37: Transportation
A38: Yun, Hyunsoo; Lee, Eun Hak; Kim, Dong-Kyu; Cho, Shin-Hyung | B38: Transp. Res. Record | C38: NOV | D38: 2021 | E38: =VLOOKUP(default_1!F41,Hoja1!$AD$1:$AE$176,2,FALSE) -> 8 | F38: 10.1177/03611981211027562 | G38: P038 | H38: Multimodal | I38: Subway;Bus | J38: 20980000 | K38: 1 | L38: 2017 | M38: Seoul, South Korea | N38: Closed | O38: 1 | P38: 1 | R38: 0 | S38: Performance indicators | T38: Accessibility | U38: Accesibility Index;Jenks’ Natural Breaks | V38: Descriptive statistics;Clustering | W38: 0 | Y38: 1 | Z38: Accesibility Index | AC38: Urban planning
A39: Zhao, Zhan; Koutsopoulos, Haris N.; Zhao, Jinhua | B39: Transp. Res. Pt. C-Emerg. Technol. | C39: JUL | D39: 2020 | E39: =VLOOKUP(default_1!F11,Hoja1!$AD$1:$AE$176,2,FALSE) -> 20 | F39: 10.1016/j.trc.2020.102627 | G39: P039 | H39: Multimodal | I39: Subway;Tram;Train | J39: 3339187 | K39: 730 | M39: London, UK | N39: Closed | O39: 1 | P39: 1 | R39: 0 | S39: Activity estimation | T39: Activity estimation | U39: LDA | V39: Natural language processing | W39: 0 | Y39: 1 | AA39: log likelihood ratios;PP | AB39: Python;Cython | AC39: Transportation
A40: Lee, Gyeongjae; Choo, Sangho; Choi, Sungtaek; Lee, Hyangsook | B40: Sustainability | C40: JUN | D40: 2022 | E40: =VLOOKUP(default_1!F18,Hoja1!$AD$1:$AE$176,2,FALSE) -> 4 | F40: 10.3390/su14127431 | G40: P040 | H40: Bus | J40: 1856015 | K40: 92 | L40: 2020 | M40: Seoul, South Korea | N40: Closed | O40: 0 | P40: 0 | Q40: Travel data;Meteorological | R40: 0 | S40: Performance indicators | T40: Travel time | U40: Geo-conv Long Short-term Memory model | V40: Deep learning | W40: 1 | X40: 1D-CNN;LSTM | Y40: 0 | Z40: Set of stops;Stop i;The latitude of stop i;The longitude of stop i;The number of passengers getting on the target bus at the stop i;The number of passengers getting off the target bus at the stop i;The number of passengers on board when the target bus arrives at the stop i;The number of passengers getting on buses other than the target bus at bus stop i;The number of passengers getting off buses other than the target bus at bus stop i;The speed of the link to which the stop i belongs;The number of lanes of the link to which the stop i belongs;Temperature around the stop i;Precipitation around the stop i;Identity of the vehicle;The time slot of the day (1 min: 1);The day of week | AA40: RMSE;MAE;MAPE | AC40: Transportation
A41: Liu, Yongxin; Li, Jianqiang; Ming, Zhong; Song, Houbing; Weng, Xiaoxiong; Wang, Jian | B41: J. Netw. Comput. Appl. | C41: MAY 15 | D41: 2019 | E41: =VLOOKUP(default_1!F93,Hoja1!$AD$1:$AE$176,2,FALSE) -> 7 | F41: 10.1016/j.jnca.2019.02.016 | G41: P041 | H41: Bus | J41: 37200000 | K41: 62 | L41: 2017 | M41: Zhuhai, China | N41: Open | O41: 0 | P41: 0 | Q41: Transit Feed;Network;POI | R41: 0 | S41: Data preprocessing | T41: Improve data quality | U41: Time discrepancy identification algorithm | V41: Authors technique | W41: 0 | Y41: 1 | Z41: Algoritmo propio | AA41: BS;SoC | AB41: C++;Qt;Echarts;Node.js | AC41: Transportation
A42: Wang, Haiyang; Li, Longyuan; Pan, Pingjun; Wang, Yongkun; Jin, Yaohui | B42: Transp. Res. Pt. C-Emerg. Technol. | C42: AUG | D42: 2019 | E42: =VLOOKUP(default_1!F91,Hoja1!$AD$1:$AE$176,2,FALSE) -> 15 | F42: 10.1016/j.trc.2019.05.022 | G42: P042 | H42: Subway | J42: 240000000 | K42: 30 | L42: 2015 | M42: Shangai, China | N42: Closed | O42: 0 | P42: 1 | Q42: Events | R42: 0 | S42: Demand forecasting | T42: Flow | U42: Early Warning Framework | V42: Time series analysis | W42: 1 | X42: ESWD (Zhu and Shasha 2003); multivariate regression;SARIMA-NLC | Y42: 1 | AA42: PPV;TPR;F-Score;MAE;RMSE | AB42: Apache Spark;Python | AC42: Transportation
A43: Wang, Ziyulong; Pel, Adam J.; Verma, Trivik; Krishnakumari, Panchamy; van Brakel, Peter; van Oort, Niels | B43: Transp. Res. Pt. C-Emerg. Technol. | C43: SEP | D43: 2022 | E43: =VLOOKUP(default_1!F16,Hoja1!$AD$1:$AE$176,2,FALSE) -> 16 | F43: 10.1016/j.trc.2022.103790 | G43: P043 | H43: Bus | J43: 160655 | K43: 31 | L43: 2019 | M43: Groningen, Netherlands;Drenthe, Netherlands | N43: Closed | O43: 0 | P43: 0 | Q43: Travel planning | R43: 0 | S43: Demand forecasting | T43: Spatio-temporal | U43: k-NN;Random forest;Gradient boosting | V43: Regression;Regression;Regression | W43: 0 | Y43: 1 | Z43: The passengers on-board per section per trip;The monthly average of ridership per trip;The autumn holiday;The trip requests per section per trip;The monthly average of requests per section per trip;The section-level variance of requests, compared to the request_mean per section per trip;Weekday or weekend;The section that a vehicle traverses during a trip;The direction of a trip;Morning peak or evening peak or off-peak hours;The passengers on-board of the same trip last week per section per trip;The trip requests that are sent 10 min ahead per section per trip;The section-level variance of requests that are sent 10 min ahead, compared to the request_mean per section per trip;The trip requests that are sent 15 min ahead per section per trip;The section-level variance of requests that are sent 15 min ahead, compared to the request_mean per section per trip;The trip requests that are sent 30 min ahead per section per trip;The section-level variance of requests that are sent 30 min ahead, compared to the request_mean per section per trip | AA43: RMSE;MAE;R² | AC43: Transportation
A44: Kim, Kyoungok | B44: J. Transp. Eng. Pt A-Syst. | C44: JUL 1 | D44: 2020 | E44: =VLOOKUP(default_1!F73,Hoja1!$AD$1:$AE$176,2,FALSE) -> 8 | F44: 10.1061/JTEPBS.0000371 | G44: P044 | H44: Multimodal | I44: Bus;Subway | J44: 4375110831 | K44: 609 | L44: 2016-2017 | M44: Seoul, South Korea | N44: Closed | O44: 0 | P44: 0 | Q44: Transit Feed;Meteorological;Social/Demographic/Economic;Land use | R44: 0 | S44: Pattern analysis | T44: Multimodal | U44: Generalized linear model | V44: Regression | W44: 0 | Y44: 1 | Z44: Travel distance between origin and destination (km);Travel time between origin and destination (min);Time divided by Dist;Number of transfers;Number of transfers divided by Dist;Number of routes provided by online map service;Walking distance to move between different bus stations for transfer;Transfer distance divided by Dist;seboth variables divided byand Res = residence.;Subway distance−bus distance;(Subway distance−bus distance)/(bus distance);Subway time−bus time;(Subway time−bus time)/(bus distance);Subway transfer−bus transfer;(Subway transfer−bus transfer)/(bus distance);Subway transfer distance−bus transfer distance;(Subway transfer distance−bus transfer distance)/(bus distance);Subway fare−bus fare;Indicator variable for temperature <0 °C;Indicator variable for 0°C ≤ temperature <10°C;Indicator variable for 10°C ≤ temperature <20°C;Indicator variable for 20°C ≤ temperature <25°C;Indicator variable for temperature ≥ 25°C;Relative humidity;Precipitation (mm);Frequency of hours with rain for a day;Wind speed (m=s);Temperature humidity index;Snowfall (cm);Indicator variable for weekends;Indicator variable for public holidays during weekdays;Indicator variable for weekends or public holidays during weekdays;Indicator variables for consecutive holidays more than 3 days;Indicator variable for (OD) = (Res, Res);Indicator variable for both (Res, Biz) and (Biz, Res) in case of undirected OD pairs or (Biz, Res) in case of directed OD pairs;Indicator variable for (Res, Biz);Indicator variable for (Biz, Biz) | AA44: pseudo-R²;R²;MSE | AB44: Python | AC44: Transportation
A45: Wang, Siqin; Liu, Yan; Corcoran, Jonathan | B45: Transp. Res. Pt. A-Policy Pract. | C45: FEB | D45: 2021 | E45: =VLOOKUP(default_1!F56,Hoja1!$AD$1:$AE$176,2,FALSE) -> 8 | F45: 10.1016/j.tra.2020.12.010 | G45: P045 | H45: Multimodal | I45: Train;Bus;Ferry | J45: 4379653 | K45: 14 | L45: 2016-2017 | M45: South East Queensland, Australia | N45: Closed | O45: 1 | P45: 1 | Q45: Transit Feed | R45: 0 | S45: Performance indicators | T45: Fare | U45: Lorenz Curves;Gini-Indexes;Descriptive statistics | V45: Economical model;Economical model;Descriptive statistics | W45: 0 | Y45: 0 | AC45: Transportation
A46: Lee, Soongbong; Lee, Jongwoo; Bae, Bumjoon; Nam, Daisik; Cheon, Seunghoon | B46: Appl. Sci.-Basel | C46: NOV | D46: 2021 | E46: =VLOOKUP(default_1!F62,Hoja1!$AD$1:$AE$176,2,FALSE) -> 5 | F46: 10.3390/app112110415 | G46: P046 | H46: Multimodal | I46: Bus;Subway | J46: 4110205036 | K46: 366 | L46: 2020 | M46: South Korea | N46: Open-Closed | O46: 0 | P46: 0 | R46: 0 | S46: Destination estimation | T46: Estimate alighting | U46: Trip-chaining algorithm | V46: Trip-chaining algorithm | W46: 0 | Y46: 0 | AA46: Accuracy | AC46: Transportation
A47: Xie, Xiaoyan; Leurent, Fabien | B47: Transp. Res. Record | D47: 2017 | E47: =VLOOKUP(default_1!F127,Hoja1!$AD$1:$AE$176,2,FALSE) -> 35 | F47: 10.3141/2648-16 | G47: P047 | H47: Train | J47: 500000 | K47: 1 | L47: 2015 | M47: Paris, France | N47: Closed | O47: 1 | P47: 1 | R47: 0 | S47: Performance indicators | T47: Transfer | U47: Stochastic modeling;OD matrix | V47: Stochastic modeling;OD matrix | W47: 1 | X47: OD matrix (Xie et al. 2015) | Y47: 0 | AA47: log likelihood ratios;Std deviation | AC47: Transportation
A48: Lee, Eun Hak; Kim, Kyoungtae; Kho, Seung-Young; Kim, Dong-Kyu; Cho, Shin-Hyung | B48: Transp. Res. Record | C48: NOV | D48: 2021 | E48: =VLOOKUP(default_1!F48,Hoja1!$AD$1:$AE$176,2,FALSE) -> 16 | F48: 10.1177/03611981211013349 | G48: P048 | H48: Subway | J48: 150127 | K48: 1 | L48: 2017 | M48: Seoul, South Korea | N48: Closed | O48: 1 | P48: 1 | R48: 0 | S48: Performance indicators | T48: Mobility performance | U48: XGBoost | V48: Classification | W48: 0 | Y48: 1 | Z48: Average waiting time;Average in-vehicel time;Average crowding;Average total travel time;Number of transfers for the express train | AA48: RMSE;Shapely values;PPV;TPR;Accuracy;F-Score | AB48: Python | AC48: Transportation
A49: Arbex, Renato; Cunha, Claudio B. | B49: J. Transp. Geogr. | C49: MAY | D49: 2020 | E49: =VLOOKUP(default_1!F78,Hoja1!$AD$1:$AE$176,2,FALSE) -> 40 | F49: 10.1016/j.jtrangeo.2020.102671 | G49: P049 | H49: Multimodal | I49: Bus;Subway;Train | J49: 260000000 | K49: 365 | L49: 2017-2018 | M49: São Paulo, Brazil | N49: Open | O49: 0 | P49: 1 | Q49: Network;Travel data;Travel data;Social/Demographic/Economic;Social/Demographic/Economic | R49: 0 | S49: Pattern analysis | T49: Social/Economic/Demographic | U49: Trip-chaining algorithm;Descriptive statistics | V49: Trip-chaining algorithm;Descriptive statistics | W49: 0 | Y49: 1 | Z49: Accesibility index;load factor;passenger density;travel time | AB49: Python | AC49: Transportation
A50: Zhao, Juanjuan; Zhang, Fan; Tu, Lai; Xu, Chengzhong; Shen, Dayong; Tian, Chen; Li, Xiang-Yang; Li, Zhengxi | B50: IEEE Trans. Intell. Transp. Syst. | C50: APR | D50: 2017 | E50: =VLOOKUP(default_1!F121,Hoja1!$AD$1:$AE$176,2,FALSE) -> 35 | F50: 10.1109/TITS.2016.2587864 | G50: P050 | H50: Subway | J50: 300000000 | K50: 60 | L50: 2015 | M50: Shenzhen, China | N50: Closed | O50: 0 | P50: 1 | Q50: Transit Feed | R50: 0 | S50: Path planning/finding | T50: Route choice | U50: Probability model | V50: Probability techniques | W50: 0 | Y50: 1 | AB50: Hadoop | AC50: Transportation
A51: Eltved, Morten; Lemaitre, Philip; Petersen, Niklas Christoffer | B51: Transp. Res. Pt. C-Emerg. Technol. | C51: NOV | D51: 2021 | E51: =VLOOKUP(default_1!F36,Hoja1!$AD$1:$AE$176,2,FALSE) -> 15 | F51: 10.1016/j.trc.2021.103332 | G51: P051 | H51: Multimodal | I51: Bus;Train | J51: 542713 | K51: 30 | L51: 2019 | M51: Eastern Denmark, Denmark | N51: Open-Closed | O51: 0 | P51: 1 | Q51: Transit Feed | R51: 0 | S51: Performance indicators | T51: Transfer | U51: Hierarchical mixture model | V51: Clustering | W51: 0 | Y51: 1 | AA51: R² | AB51: Stan (NUTS) | AC51: Transportation
A52: Shelat, Sanmay; Cats, Oded; van Oort, Niels; van Lint, J. W. C. | B52: Transportmetrica A | C52: MAR 15 | D52: 2023 | E52: =VLOOKUP(default_1!F28,Hoja1!$AD$1:$AE$176,2,FALSE) -> 168 | F52: 10.1080/23249935.2022.2028929 | G52: P052 | H52: Multimodal | I52: Bus;Tram | J52: 5900000 | K52: 31 | L52: 2015 | M52: The Hague, Netherlands | N52: Closed | O52: 0 | P52: 1 | Q52: Transit Feed | R52: 0 | S52: Path planning/finding | T52: Route choice | U52: Multinomial logit | V52: Regression | W52: 0 | Y52: 1 | AA52: log likelihood ratios | AB52: Python | AC52: Transportation
A53: Liu, Xintao; Lin, Ziwei; Huang, Jianwei; Gao, He; Shi, Wenzhong | B53: Int. J. Environ. Res. Public Health | C53: MAR | D53: 2021 | E53: =VLOOKUP(default_1!F53,Hoja1!$AD$1:$AE$176,2,FALSE) -> 8 | F53: 10.3390/ijerph18052711 | G53: P053 | H53: Multimodal | I53: Bus;Subway | J53: 30620366 | K53: 7 | L53: 2016 | M53: Beijing, China | N53: Closed | O53: 0 | P53: 0 | Q53: Layers;Social/Demographic/Economic | R53: 0 | S53: Pattern analysis | T53: Social/Economic/Demographic | U53: Gravity-based model;Spatial Durbin Model | V53: Gravity-based model;Regression | W53: 0 | Y53: 1 | AA53: Moran's I;R² | AB53: Python | AC53: Public health
A54: Yu, Wei; Ye, Xiaofei; Chen, Jun; Yan, Xingchen; Wang, Tao | B54: Sustainability | C54: FEB | D54: 2020 | E54: =VLOOKUP(default_1!F85,Hoja1!$AD$1:$AE$176,2,FALSE) -> 129 | F54: 10.3390/su12031113 | G54: P054 | H54: Subway | J54: 6300015 | K54: 5 | L54: 2016 | M54: Nanjing, China | N54: Closed | O54: 1 | P54: 1 | R54: 0 | S54: Performance indicators | T54: Travel time | U54: Descriptive statistics | V54: Descriptive statistics | W54: 0 | Y54: 1 | Z54: use time probability;passenger flow between stations; average time between stations; and time variance between stations;Space P Model and Minimum Number of Rides;Ride Time Model and Shortest Ride Time;Flow Efficiency between Stations;Network Flow Efficiency | AA54: Correlation coefficient | AB54: Matlab;UCINET | AC54: Transportation
A55: Song, Ji Young; Eom, Jin Ki; Kim, Sung Il | B55: Promet | D55: 2014 | E55: =VLOOKUP(default_1!F138,Hoja1!$AD$1:$AE$176,2,FALSE) -> 5 | F55: 10.7307/ptt.v26i4.1394 | G55: P055 | H55: Multimodal | I55: Bus;Subway | J55: 105000000 | K55: 3 | L55: 2012 | M55: Seoul, South Korea | N55: Closed | O55: 1 | P55: 1 | R55: 0 | S55: Pattern analysis | T55: Social/Economic/Demographic | U55: Random Utility Model;Multinomial logit | V55: Regression;Regression | W55: 0 | Y55: 1 | AA55: R²;t-Value;log likelihood ratios | AC55: Socio-economic / demographic
A56: Dixit, Malvika; Chowdhury, Subeh; Cats, Oded; Brands, Ties; van Oort, Niels; Hoogendoorn, Serge | B56: J. Transp. Geogr. | C56: FEB | D56: 2021 | E56: =VLOOKUP(default_1!F54,Hoja1!$AD$1:$AE$176,2,FALSE) -> 9 | F56: 10.1016/j.jtrangeo.2021.102980 | G56: P056 | H56: Multimodal | I56: Bus;Subway;Tram | J56: 23625000 | K56: 35 | L56: 2018 | M56: Amsterdam, Netherlands | N56: Closed | O56: 0 | P56: 0 | Q56: Social/Demographic/Economic | R56: 0 | S56: Pattern analysis | T56: Social/Economic/Demographic | U56: Ordinary least squares;Lagrange Multiplier;Spatial Error | V56: Regression;Optimization;Regression | W56: 0 | Y56: 1 | Z56: Transit circuity | AA56: log likelihood ratios;AIC;Moran's I;Gini coefficient | AC56: Socio-economic / demographic
A57: Kandt, Jens; Leak, Alistair | B57: J. Transp. Geogr. | C57: JUL | D57: 2019 | E57: =VLOOKUP(default_1!F92,Hoja1!$AD$1:$AE$176,2,FALSE) -> 42 | F57: 10.1016/j.jtrangeo.2019.102474 | G57: P057 | H57: Multimodal | I57: Bus;Tram | J57: 300000000 | K57: 2118 | L57: 2010-2016 | M57: West Midlands Combined Authority, UK | N57: Open | O57: 1 | P57: 1 | R57: 0 | S57: Pattern analysis | T57: Social/Economic/Demographic | U57: Hamming algorithm;Ward's algorithm;Multinomial logit | V57: Error correction model;Clustering;Regression | W57: 0 | Y57: 1 | AA57: DIC;Moran's I | AB57: R | AC57: Socio-economic / demographic
A58: Liu, Shasha; Yamamoto, Toshiyuki; Yao, Enjian; Nakamura, Toshiyuki | B58: J. Transp. Geogr. | C58: MAY | D58: 2021 | E58: =VLOOKUP(default_1!F51,Hoja1!$AD$1:$AE$176,2,FALSE) -> 9 | F58: 10.1016/j.jtrangeo.2021.103046 | G58: P058 | H58: Multimodal | I58: Bus;Tram | J58: 23450000 | K58: 365 | L58: 2018-2019 | M58: Shizuoka, Japan | N58: Closed | O58: 1 | P58: 1 | R58: 0 | S58: Pattern analysis | T58: Social/Economic/Demographic | U58: Day-to-day variability model;k-means++ | V58: Authors technique;Clustering | W58: 0 | Y58: 0 | Z58: Entropy;average similarity | AA58: DBI;t-Value;Std deviation | AC58: Socio-economic / demographic
A59: Gan, Zuoxian; Yang, Min; Feng, Tao; Timmermans, Harry J. P. | B59: Transport. Res. Part D-Transport. Environ. | C59: MAY | D59: 2020 | E59: =VLOOKUP(default_1!F79,Hoja1!$AD$1:$AE$176,2,FALSE) -> 286 | F59: 10.1016/j.trd.2020.102332 | G59: P059 | H59: Subway | J59: 43000000 | K59: 30 | L59: 2015 | M59: Nanjing, China | N59: Closed | O59: 0 | P59: 1 | Q59: Land use;Social/Demographic/Economic;Web mapping service;Web mapping service;Social/Demographic/Economic | R59: 0 | S59: Demand forecasting | T59: Spatio-temporal | U59: Direct Ridership Model;Ordinary least squares;Gradient boosting | V59: Time series analysis;Regression;Regression | W59: 0 | Y59: 0 | AA59: pseudo-R² | AC59: Socio-economic / demographic
A60: Gao, Qi-Li; Li, Qing-Quan; Yue, Yang; Zhuang, Yan; Chen, Zhi-Peng; Kong, Hui | B60: Comput. Environ. Urban Syst. | C60: NOV | D60: 2018 | E60: =VLOOKUP(default_1!F107,Hoja1!$AD$1:$AE$176,2,FALSE) -> 2 | F60: 10.1016/j.compenvurbsys.2018.02.006 | G60: P060 | H60: Multimodal | I60: Bus;Subway | J60: 2190000000 | K60: 365 | L60: 2015 | M60: Shenzhen, China | N60: Open-Closed | O60: 1 | P60: 1 | R60: 0 | S60: Pattern analysis | T60: Social/Economic/Demographic | U60: Jenks’ Natural Breaks | V60: Clustering | W60: 0 | Y60: 0 | Z60: NFR;inflow;outflow | AC60: Socio-economic / demographic
A61: Ghasemlou, Kiarash; Ergun, Murat; Dadashzadeh, Nima | B61: Sensors | C61: MAY | D61: 2021 | E61: =VLOOKUP(default_1!F50,Hoja1!$AD$1:$AE$176,2,FALSE) -> 95 | F61: 10.3390/s21093039 | G61: P061 | H61: Bus | J61: 12250983 | K61: 30 | L61: 2018 | M61: Kocaeli, Turkey | N61: Open | O61: 0 | P61: 1 | Q61: Transit Feed | R61: 0 | S61: Classification | T61: Social/Economic/Demographic | U61: ID-based dataset clustering;Card ID-based analysis;Route-based analysis | V61: Clustering;Descriptive statistics;Descriptive statistics | W61: 0 | Y61: 0 | AB61: Python;Excel;SQL | AC61: Transportation
A62: Zhao, Xia; Cui, Mengying; Levinson, David | B62: Env. Plan. B-Urban Anal. City Sci. | C62: JAN | D62: 2023 | E62: =VLOOKUP(default_1!F20,Hoja1!$AD$1:$AE$176,2,FALSE) -> 29 | F62: 10.1177/23998083221089662 | G62: P062 | H62: Multimodal | I62: Bus;Subway | J62: 769413168 | K62: 120 | L62: 2015 | M62: Beijing, China | N62: Closed | O62: 1 | P62: 1 | R62: 0 | S62: Pattern analysis | T62: Spatio-temporal | U62: k-means++;Multivariate ordinary least square regression;Probability distribution functions | V62: Clustering;Regression;Probability techniques | W62: 0 | Y62: 1 | Z62: SSE and SSB (Kumar et al., 2018; Han et al., 2012; Zhao et al., 2019) | AA62: F-Score;PPV;TPR;R² | AC62: Transportation
A63: Ning, Jiang; Lyu, Tao; Wang, Yuanqing | B63: J. Adv. Transp. | C63: NOV 13 | D63: 2021 | E63: =VLOOKUP(default_1!F34,Hoja1!$AD$1:$AE$176,2,FALSE) -> 5 | F63: 10.1155/2021/9966794 | G63: P063 | H63: Subway | J63: 6040000 | K63: 7 | L63: 2019 | M63: Qingdao, China | N63: Closed | O63: 0 | P63: 1 | Q63: POI | R63: 0 | S63: Pattern analysis | T63: Urban planning | U63: Negative binomial regression;Fractional response | V63: Regression;Regression | W63: 0 | Y63: 1 | Z63: elderly and student proportion | AA63: VIF | AC63: Socio-economic / demographic
A64: Liu, Shasha; Yamamoto, Toshiyuki; Yao, Enjian; Nakamura, Toshiyuki | B64: IEEE Trans. Intell. Transp. Syst. | C64: MAY | D64: 2022 | E64: =VLOOKUP(default_1!F22,Hoja1!$AD$1:$AE$176,2,FALSE) -> 7 | F64: 10.1109/TITS.2020.3043021 | G64: P064 | H64: Multimodal | I64: Bus;Train | J64: 23510000 | K64: 364 | L64: 2018-2019 | M64: Shizuoka, Japan | N64: Closed | O64: 1 | P64: 1 | R64: 0 | S64: Pattern analysis | T64: Social/Economic/Demographic | U64: DBSCAN | V64: Clustering | W64: 0 | Y64: 0 | Z64: Levenshtein distance | AA64: DBI | AC64: Socio-economic / demographic
A65: Chen, Wendong; Liu, Xize; Chen, Xuewu; Cheng, Long; Wang, Kailai; Chen, Jingxu | B65: Travel Behav. Soc. | C65: JUL | D65: 2022 | E65: =VLOOKUP(default_1!F25,Hoja1!$AD$1:$AE$176,2,FALSE) -> 123 | F65: 10.1016/j.tbs.2022.02.005 | G65: P065 | H65: Bike | J65: 2700000 | K65: 35 | L65: 2016-2020 | M65: Nanjing, China | N65: Closed | O65: 0 | P65: 1 | Q65: Social/Demographic/Economic;Network | R65: 0 | S65: Pattern analysis | T65: Spatio-temporal | U65: Spatial cluster partitioning algorithm | V65: Clustering | W65: 0 | Y65: 1 | AA65: t-Value | AC65: Socio-economic / demographic
A66: Chen, Ruoyu; Zhou, Jiangping | B66: Transp. Res. Pt. A-Policy Pract. | C66: OCT | D66: 2022 | E66: =VLOOKUP(default_1!F12,Hoja1!$AD$1:$AE$176,2,FALSE) -> 6 | F66: 10.1016/j.tra.2022.08.003 | G66: P066 | H66: Subway | J66: 8160000 | K66: 168 | L66: 2018-2019 | M66: Wuhan, China | N66: Closed | O66: 1 | P66: 1 | R66: 0 | S66: Pattern analysis | T66: Social/Economic/Demographic | U66: LDA;Descriptive statistics | V66: Natural language processing;Descriptive statistics | W66: 0 | Y66: 0 | Z66: Trip frequency;Destination stickiness index | AA66: t-Value | AB66: Matlab | AC66: Transportation
A67: Huang, Ailing; Dou, Ziqi; Qi, Liuzi; Wang, Lewen | B67: J. Transp. Eng. Pt A-Syst. | C67: DEC 1 | D67: 2020 | E67: =VLOOKUP(default_1!F65,Hoja1!$AD$1:$AE$176,2,FALSE) -> 22 | F67: 10.1061/JTEPBS.0000448 | G67: P067 | H67: Subway | J67: 366427 | K67: 1 | L67: 2017 | M67: Beijing, China | N67: Closed | O67: 1 | P67: 1 | R67: 0 | S67: Path planning/finding | T67: Custom routes | U67: Dynamic genetic algorithm | V67: Genetic algorithm | W67: 0 | Y67: 0 | AB67: Matlab | AC67: Transportation
A68: Schmoecker, Jan-Dirk; Shimamoto, Hiroshi; Kurauchi, Fumitaka | B68: Transp. Res. Pt. C-Emerg. Technol. | C68: NOV | D68: 2013 | E68: =VLOOKUP(default_1!F139,Hoja1!$AD$1:$AE$176,2,FALSE) -> 2 | F68: 10.1016/j.trc.2013.06.014 | G68: P068 | H68: Bus | J68: 2100285 | K68: 61 | L68: 2011 | M68: Japan | N68: Closed | O68: 1 | P68: 1 | R68: 0 | S68: Path planning/finding | T68: Route choice | U68: Generation logit model;Cross-nested Logit model;Multinomial logit | V68: Regression;Regression;Regression | W68: 1 | X68: Generation logit model (Swait 2001) | Y68: 1 | Z68: scale parameter;likelihood function | AA68: log likelihood ratios;t-Value | AB68: Matlab | AC68: Transportation
A69: Shi, Zhuangbin; Liu, Yang; He, Mingwei; Liu, Qiyang | B69: J. Adv. Transp. | C69: AUG 22 | D69: 2022 | E69: =VLOOKUP(default_1!F10,Hoja1!$AD$1:$AE$176,2,FALSE) -> 1 | F69: 10.1155/2022/2080552 | G69: P069 | H69: Subway | J69: 5810000 | K69: 120 | L69: 2019 | M69: Nanjing, China | N69: Closed | O69: 0 | P69: 1 | Q69: POI | R69: 0 | S69: Pattern analysis | T69: Social/Economic/Demographic | U69: Gradient boosting | V69: Regression | W69: 0 | Y69: 1 | Z69: Environmental variables (Tabla 2) | AA69: R²;VIF | AC69: Socio-economic / demographic
A70: Yen, Barbara T. H.; Mulley, Corinne; Yeh, Chia -Jung | B70: J. Transp. Geogr. | C70: APR | D70: 2023 | E70: =VLOOKUP(default_1!F3,Hoja1!$AD$1:$AE$176,2,FALSE) -> 7 | F70: 10.1016/j.jtrangeo.2023.103569 | G70: P070 | H70: Multimodal | I70: Bike;Subway | J70: 509857723 | K70: 244 | L70: 2018 | M70: Taipei City, Taiwan | N70: Closed | O70: 0 | P70: 1 | Q70: POI | R70: 0 | S70: Performance indicators | T70: Accessibility | U70: Time saving algorithm | V70: Authors technique | W70: 0 | Y70: 0 | Z70: Travel time savings;walking speed (Bohannon and Andrews,2011; Fruin, 1971) | AC70: Transportation
A71: Xue, Gang; Liu, Shifeng; Gong, Daqing | B71: IEEE Trans. Intell. Transp. Syst. | C71: APR | D71: 2022 | E71: =VLOOKUP(default_1!F24,Hoja1!$AD$1:$AE$176,2,FALSE) -> 10 | F71: 10.1109/TITS.2020.3032843 | G71: P071 | H71: Subway | J71: 1956000000 | K71: 164 | L71: 2017-2018 | M71: Beijing, China | N71: Closed | O71: 1 | P71: 1 | R71: 0 | S71: Anomaly detection | T71: Passengers behaviour | U71: k-means;Convolutional neural networks;Densely Connected Convolutional Networks | V71: Clustering;Deep learning;Deep learning | W71: 0 | Y71: 1 | Z71: IOSSS | AA71: Silhouette score;PPV;TPR;F-Score | AB71: Python;TensorFlow | AC71: Transportation
A72: Zhang, Tong; Li, Yicong; Yang, Hui; Cui, Chenrong; Li, Jing; Qiao, Qinghua | B72: Int. J. Geogr. Inf. Sci. | C72: JUN 2 | D72: 2020 | E72: =VLOOKUP(default_1!F75,Hoja1!$AD$1:$AE$176,2,FALSE) -> 146 | F72: 10.1080/13658816.2018.1554812 | G72: P072 | H72: Multimodal | I72: Bus;Subway | J72: 51800000 | K72: 7 | L72: 2017 | M72: Shenzhen, China | N72: Open-Closed | O72: 0 | P72: 1 | Q72: Transit Feed;Network | R72: 0 | S72: Passengers flow | T72: Spatio-temporal | U72: PageRank;Clauset–Newman–Moore;Combo;Normalized Mutual Information | V72: Ranking algorithm;Graph model;Graph model;Graph model | W72: 0 | Y72: 1 | Z72: Transit flow;Accumulated transit flow;transit flow density;shared (accumulated) transit flow | AA72: PPV;TPR;F-Score | AB72: C++ | AC72: Transportation
A73: Brands, Ties; Dixit, Malvika; van Oort, Niels | B73: Eur. J. Transport. Infrastruct. Res. | C73: DEC 21 | D73: 2020 | E73: =VLOOKUP(default_1!F111,Hoja1!$AD$1:$AE$176,2,FALSE) -> 6 | F73: 10.18757/ejtir.2020.20.4.4084 | G73: P073 | H73: Multimodal | I73: Bus;Tram;Subway | J73: 588000000 | K73: 84 | L73: 2017-2018 | M73: Amsterdam, Netherlands | N73: Closed | O73: 1 | P73: 1 | R73: 0 | S73: Pattern analysis | T73: Social/Economic/Demographic | U73: Agglomerative hierarchical clustering | V73: Clustering | W73: 0 | X73: Jain et al., 1999 | Y73: 1 | Z73: number of travellers; travel time; transfer time; number of transfers; travel time reliability | AA73: Std deviation | AC73: Transportation
A74: Eltved, Morten; Breyer, Nils; Ingvardson, Jesper Blafoss; Nielsen, Otto Anker | B74: Transp. Res. Pt. C-Emerg. Technol. | C74: OCT | D74: 2021 | E74: =VLOOKUP(default_1!F109,Hoja1!$AD$1:$AE$176,2,FALSE) -> 16 | F74: 10.1016/j.trc.2021.103198 | G74: P074 | H74: Subway | K74: 270 | L74: 2018 | M74: Greater Copenhagen area, Denmark | N74: Closed | O74: 1 | P74: 1 | R74: 0 | S74: Pattern analysis | T74: Spatio-temporal | U74: k-means;Agglomerative hierarchical clustering | V74: Clustering;Clustering | W74: 0 | Y74: 1 | Z74: number of trips; start time of trip; other features describing travel behaviour; features describing daily travel activity | AA74: Correlation coefficient | AC74: Transportation
A75: Zhou, Meng; Wang, Donggen; Li, Qingquan; Yue, Yang; Tu, Wei; Cao, Rui | B75: Transp. Res. Pt. C-Emerg. Technol. | C75: FEB | D75: 2017 | E75: =VLOOKUP(default_1!F123,Hoja1!$AD$1:$AE$176,2,FALSE) -> 13 | F75: 10.1016/j.trc.2016.12.001 | G75: P075 | H75: Multimodal | I75: Bus;Subway | J75: 105000000 | K75: 30 | L75: 2014 | M75: Shenzhen, China | N75: Open-Closed | O75: 0 | P75: 1 | Q75: Meteorological;Network;Network;Layers;Layers | R75: 0 | S75: Pattern analysis | T75: Meteorological | U75: Multivariate regression model | V75: Regression | W75: 0 | Y75: 1 | Z75: public transit ridership; temperature; relative humidity; air pressure; wind speed; rainfall | AA75: F-Score;R² | AC75: Transportation
A76: Assemi, Behrang; Alsger, Azalden; Moghaddam, Mahboobeh; Hickman, Mark; Mesbah, Mahmoud | B76: Public Transport | C76: MAR | D76: 2020 | E76: =VLOOKUP(default_1!F81,Hoja1!$AD$1:$AE$176,2,FALSE) -> 105 | F76: 10.1007/s12469-019-00218-9 | G76: P076 | H76: Multimodal | I76: Bus;Train;Ferry | J76: 160000 | K76: 1 | L76: 2013 | M76: South East Queensland, Australia | N76: Closed | O76: 0 | P76: 1 | Q76: Layers;Layers | R76: 0 | S76: Origin-Destination | T76: Trip chain | U76: Single-layer perceptron neural networks;Alighting estimation algorithm | V76: Neural networks;Deep learning | W76: 1 | X76: Nassir et al., 2011 | Y76: 1 | Z76: date; run; route; direction; smartcard ID; boarding time; alighting time; boarding stop; alighting stop | AA76: t-Value;R² | AB76: R | AC76: Transportation
A77: Yap, M. D.; Nijenstein, S.; van Oort, N. | B77: Transp. Policy | C77: JAN | D77: 2018 | E77: =VLOOKUP(default_1!F117,Hoja1!$AD$1:$AE$176,2,FALSE) -> 3 | F77: 10.1016/j.tranpol.2017.10.010 | G77: P077 | H77: Bus | J77: 7500000 | K77: 25 | L77: 2015 | M77: The Hague, Netherlands | N77: Closed | O77: 1 | P77: 1 | R77: 0 | S77: Performance indicators | T77: Mobility performance | U77: Ridership prediction model;Rule-based procedure | V77: Regression;Authors technique | W77: 1 | X77: Van Oort et al. (2015a) | Y77: 1 | Z77: in-vehicle travel time; transfer walking time; waiting time; number of transfers; travel fares | AA77: R² | AC77: Transportation
A78: Tang, Tianli; Liu, Ronghui; Choudhury, Charisma | B78: Sust. Cities Soc. | C78: FEB | D78: 2020 | E78: =VLOOKUP(default_1!F74,Hoja1!$AD$1:$AE$176,2,FALSE) -> 20 | F78: 10.1016/j.scs.2019.101927 | G78: P078 | H78: Bus | J78: 17159076 | K78: 183 | L78: 2016 | M78: Changsha, China | N78: Open | O78: 0 | P78: 0 | Q78: Meteorological | R78: 0 | S78: Destination estimation | T78: Estimate alighting | U78: Multi-class gradient boosting decision tree | V78: Regression | W78: 0 | Y78: 1 | Z78: Month;Day;Hour;Days of week;Holiday;Boarding stop ID;Boarding line;Number of trips on the previous day;Number of trips on the same day of the last week;Number of trips in the same hour on the same day of the last week;temperature;PRecipitation;Humidity;Visibility;Wind speed;Weather events | AA78: PPV;TPR;F-Score;GEH | AC78: Transportation
A79: Trepanier, Martin; Tranchant, Nicolas; Chapleau, Robert | B79: J. Intell. Transport. Syst. | D79: 2007 | E79: =VLOOKUP(default_1!F104,Hoja1!$AD$1:$AE$176,2,FALSE) -> 33 | F79: 10.1080/15472450601122256 | G79: P079 | H79: Bus | J79: 1149499 | K79: 62 | L79: 2003 | M79: Gatineau, Canada | N79: Open | O79: 1 | P79: 1 | R79: 0 | S79: Destination estimation | T79: Estimate alighting | U79: Trip destination estimation model | V79: Trip destinaton model | W79: 0 | Y79: 1 | AA79: Accuracy | AB79: Visual Basic for Applications;Microsoft Access | AC79: Transportation
A80: Cerqueira, Sofia; Arsenio, Elisabete; Henriques, Rui | B80: Eur. Transp. Res. Rev. | C80: DEC | D80: 2022 | E80: =VLOOKUP(default_1!F6,Hoja1!$AD$1:$AE$176,2,FALSE) -> 78 | F80: 10.1186/s12544-022-00562-1 | G80: P080 | H80: Multimodal | I80: Bus;Subway | J80: 42000000 | K80: 31 | L80: 2019 | M80: Lisbon, Portugal | N80: Open-Closed | O80: 1 | P80: 1 | R80: 0 | S80: Origin-Destination | T80: OD Matrix Generation | U80: OD matrix | V80: OD matrix | W80: 0 | Y80: 0 | AB80: Python;SQL;Plotly.js | AC80: Transportation
A81: Zhong, Chen; Huang, Xianfeng; Arisona, Stefan Mueller; Schmitt, Gerhard; Batty, Michael | B81: Comput. Environ. Urban Syst. | C81: NOV | D81: 2014 | E81: =VLOOKUP(default_1!F21,Hoja1!$AD$1:$AE$176,2,FALSE) -> 10 | F81: 10.1016/j.compenvurbsys.2014.07.004 | G81: P081 | H81: Bus | J81: 896000 | K81: 7 | L81: 2011 | M81: Singapore | N81: Closed | O81: 0 | P81: 0 | Q81: Survey | R81: 0 | S81: Activity estimation | T81: Urban planning | U81: Naïve Bayes;Probability model | V81: Regression;Probability techniques | W81: 0 | Y81: 1 | Z81: Alighting time;Age distribution;Activity frequency;Staying time;Walking distance;Location | AC81: Urban planning
A82: Hossain, Sanjana; Habib, Khandker Nurul | B82: Transp. Res. Pt. A-Policy Pract. | C82: NOV | D82: 2022 | E82: =VLOOKUP(default_1!F8,Hoja1!$AD$1:$AE$176,2,FALSE) -> 0 | F82: 10.1016/j.tra.2022.09.010 | G82: P082 | H82: Multimodal | I82: Bus;Subway;Train;Tram | J82: 2727421 | K82: 5 | L82: 2016 | M82: Greater Toronto and Hamilton Area, Canada | N82: Open-Closed | O82: 0 | P82: 0 | Q82: POI;Land use;Network;Survey | R82: 0 | S82: Origin-Destination | T82: OD Matrix Generation | U82: Data fusion;Multinomial logit | V82: Authors technique;Regression | W82: 0 | X82: MMNL | Y82: 1 | AA82: AIC;BIC;t-Value;log likelihood ratios;log likelihood ratios | AC82: Transportation
A83: Langlois, Gabriel Goulet; Koutsopoulos, Haris N.; Zhao, Jinhua | B83: Transp. Res. Pt. C-Emerg. Technol. | C83: MAR | D83: 2016 | E83: =VLOOKUP(default_1!F130,Hoja1!$AD$1:$AE$176,2,FALSE) -> 15 | F83: 10.1016/j.trc.2015.12.012 | G83: P083 | H83: Multimodal | I83: Bus;Subway | J83: 3000000 | K83: 29 | L83: 2014 | M83: London, UK | N83: Open-Closed | O83: 0 | P83: 1 | Q83: Survey | R83: 0 | S83: Pattern analysis | T83: Spatio-temporal | U83: Agglomerative hierarchical clustering;PCA;Multinomial logit;k-means | V83: Clustering;Dimensionality reduction;Regression;Clustering | W83: 1 | X83: Gordon et al. 2013 | Y83: 0 | AA83: R² | AB83: Python | AC83: Transportation
A84: Lei, Da; Chen, Xuewu; Cheng, Long; Zhang, Lin; Ukkusuri, Satish, V; Witlox, Frank | B84: Transp. Res. Pt. C-Emerg. Technol. | C84: NOV | D84: 2020 | E84: =VLOOKUP(default_1!F68,Hoja1!$AD$1:$AE$176,2,FALSE) -> 43 | F84: 10.1016/j.trc.2020.102810 | G84: P084 | H84: Multimodal | I84: Subway;Bike | J84: 34855623 | K84: 28 | L84: 2017 | M84: Nanjing, China | N84: Closed | O84: 0 | P84: 0 | Q84: Layers;Land use;Network | R84: 0 | S84: Pattern analysis | T84: Spatio-temporal | U84: Temporal motif enumeration algorithm | V84: Graph model | W84: 1 | X84: Paranjape et al. 2017 | Y84: 0 | AC84: Transportation
A85: Arana, P.; Cabezudo, S.; Penalba, M. | B85: Transp. Res. Pt. A-Policy Pract. | C85: JAN | D85: 2014 | E85: =VLOOKUP(default_1!F137,Hoja1!$AD$1:$AE$176,2,FALSE) -> 3 | F85: 10.1016/j.tra.2013.10.019 | G85: P085 | H85: Bus | J85: 35000000 | K85: 730 | L85: 2010-2011 | M85: Gipuzkoa, Spain | N85: Open | O85: 0 | P85: 0 | Q85: Meteorological | R85: 0 | S85: Demand forecasting | T85: Meteorological | U85: Multivariable regression model | V85: Regression | W85: 0 | Y85: 0 | AA85: R² | AB85: SPSS | AC85: Transportation
A86: Benavente, Juan; Alonso, Borja; Rodriguez, Andres; Luis Moura, Jose | B86: IEEE Access | D86: 2021 | E86: =VLOOKUP(default_1!F43,Hoja1!$AD$1:$AE$176,2,FALSE) -> 6 | F86: 10.1109/ACCESS.2021.3107833 | G86: P086 | H86: Bus | J86: 2586000 | K86: 365 | M86: Santander, Spain | N86: Open | O86: 1 | P86: 1 | R86: 0 | S86: Data preprocessing | T86: Improve data quality | U86: AVL, Fare and Schedule integration model;Dwell time model;Trip-chaining algorithm;Anomaly detection | V86: Authors technique;Forecasting;Trip-chaining algorithm;Anomaly detection | W86: 0 | Y86: 1 | AA86: MAE;accuracy | AB86: SQL;Python;Bokeh | AC86: Transportation
A87: Siripanich, Amarin; Rashidi, Taha Hossein; Moylan, Emily | B87: Sustainability | C87: MAY 1 | D87: 2019 | E87: =VLOOKUP(default_1!F94,Hoja1!$AD$1:$AE$176,2,FALSE) -> 11 | F87: 10.3390/su11092709 | G87: P087 | H87: Multimodal | I87: Bus;Train;Ferry | J87: 600000 | K87: 1 | L87: 2013 | M87: Brisbane, Australia | N87: Closed | O87: 0 | P87: 0 | Q87: Social/Demographic/Economic;Social/Demographic/Economic;Social/Demographic/Economic | R87: 0 | S87: Pattern analysis | T87: Social/Economic/Demographic | U87: Ordinary least squares;Spatial lag;Spatial Error;GWR | V87: Regression;Regression;Regression;Regression | W87: 0 | Y87: 0 | Z87: Price of the property;Number of bedrooms;Number of bathrooms;Number of car spaces;Property’s type (house = 0, unit = 1);Percentage of people with weekly income greater than $1500;Percentage of people aged greater than 65;Population density in the statistical area (1000 persons);Percentage of household residential location changed since last year;Percentage of unemployed persons;Number of trips originated during the morning peak hours (1000s of trips);Number of trips originated during the evening peak hours (1000s of trips);Proportion of transfer trips of all originated trips;Average travel time variability (min);Travel time delay during the morning peak hours (min);Trips to CBD (1000s of trips);The number of bus stops within 400 m of the property;The property is located within 400 m within to a rail station (yes = 1, no = 0);The property is located within 800 m to a ferry station (yes = 1, no = 0);Jobs accessible within a 30-min journey by public transit services (1000s of jobs);Network distance from the statistical zone where the property is located to the CBD (km) | AA87: Lagrange multiplier test;BP;Moran's I;VIF;AIC;R²;t-Value | AB87: R | AC87: Transportation
A88: Zhao, Xia; Zhang, Yong; Hu, Yongli; Wang, Shun; Li, Yunhui; Qian, Sean; Yin, Baocai | B88: IEEE Trans. Intell. Transp. Syst. | C88: AUG | D88: 2021 | E88: =VLOOKUP(default_1!F42,Hoja1!$AD$1:$AE$176,2,FALSE) -> 30 | F88: 10.1109/TITS.2020.2983853 | G88: P088 | H88: Multimodal | I88: Subway;Bus | J88: 205 | K88: 31 | L88: 2015 | M88: Beijing, China | N88: Closed | O88: 0 | P88: 0 | Q88: Travel data | R88: 0 | S88: Anomaly detection | T88: Passengers behaviour | U88: k-means++;Group mobility correlation;Individual correlation | V88: Clustering;Clustering;OD matrix | W88: 0 | Y88: 1 | Z88: visiting frequency to crime-prone station;spatial chaos in visiting diverse station zones;overall temporal chaos in visiting diverse stations;proportion of trips generated in rush hours over total;proportion of frequent travel weekdays over overall weekdays:proportion of the most freuqently-taken OD pair;proportion of short trips over total;anomaly extent of passenger against his neighbors;ICCM | AA88: Variance analysis;t-Value | AB88: Hadoop;Python;Baidu Map API;HTML5;JS | AC88: Transportation
A89: Berggren, Ulrik; D'Agostino, Carmelo; Svensson, Helena; Brundell-Freij, Karin | B89: Transportation | C89: DEC | D89: 2022 | E89: =VLOOKUP(default_1!F39,Hoja1!$AD$1:$AE$176,2,FALSE) -> 42 | F89: 10.1007/s11116-021-10218-z | G89: P089 | H89: Multimodal | I89: Bus;Train | J89: 2835249 | K89: 30 | L89: 2016-2017 | M89: South-West Scania, Sweden | N89: Open-Closed | O89: 0 | P89: 0 | Q89: Layers | R89: 0 | S89: Path planning/finding | T89: Route choice | U89: Fixed effects;Logistic regression | V89: Regression;Regression | W89: 0 | Y89: 1 | AA89: pseudo-R²;ROC curve;R²;TPR | AB89: SAS | AC89: Transportation
A90: de Regt, Karin; Cats, Oded; Van Oort, Niels; van Lint, Hans | B90: Transp. Res. Record | D90: 2017 | E90: =VLOOKUP(default_1!F124,Hoja1!$AD$1:$AE$176,2,FALSE) -> 9 | F90: 10.3141/2652-06 | G90: P090 | H90: Multimodal | I90: Bus;Subway;Tram | K90: 105 | L90: 2015 | M90: Rotterdam, Netherlands | N90: Closed | O90: 0 | P90: 0 | Q90: Mobile | R90: 0 | S90: Demand forecasting | T90: Spatio-temporal | U90: Data fusion | V90: Authors technique | W90: 0 | Y90: 1 | AA90: MPE | AB90: Matlab;ArcGIS;Python | AC90: Transportation
A91: Wang, Liu; Zhang, Yong; Zhao, Xia; Liu, Hao; Zhang, Ke | B91: IEEE Trans. Intell. Transp. Syst. | C91: MAY | D91: 2020 | E91: =VLOOKUP(default_1!F80,Hoja1!$AD$1:$AE$176,2,FALSE) -> 7 | F91: 10.1109/TITS.2019.2933497 | G91: P091 | H91: Subway | J91: 130000000 | K91: 21 | L91: 2015 | M91: Beijing, China | N91: Closed | O91: 0 | P91: 0 | Q91: Network;Social network | R91: 0 | S91: Anomaly detection | T91: Passengers behaviour | U91: k-means;DBSCAN | V91: Clustering;Clustering | W91: 0 | Y91: 1 | AA91: Silhouette score | AC91: Transportation
A92: Wang, Jinzhong; Kong, Xiangjie; Rahim, Azizur; Xia, Feng; Tolba, Amr; Al-Makhadmeh, Zafer | B92: IEEE Access | D92: 2017 | E92: =VLOOKUP(default_1!F126,Hoja1!$AD$1:$AE$176,2,FALSE) -> 39 | F92: 10.1109/ACCESS.2017.2766237 | G92: P092 | H92: Subway | J92: 451000000 | K92: 30 | L92: 2015 | M92: Shanghai, China | N92: Closed | O92: 0 | P92: 0 | Q92: POI;Network | R92: 0 | S92: Pattern analysis | T92: Urban planning | U92: IS2Fun | V92: Natural language processing | W92: 1 | X92: Doc2vec;TF-IDF | Y92: 1 | Z92: Average trip displacement (km);average trip duration (min);Average trip interval (min) | AC92: Urban planning
A93: Viggiano, Cecilia; Koutsopoulos, Haris N.; Wilson, Nigel H. M.; Attanucci, John | B93: Public Transport | C93: JUL | D93: 2017 | E93: =VLOOKUP(default_1!F119,Hoja1!$AD$1:$AE$176,2,FALSE) -> 23 | F93: 10.1007/s12469-016-0145-8 | G93: P093 | H93: Multimodal | I93: Bus;Subway;Train;Tram | K93: 14 | M93: London, UK | N93: Open-Closed | O93: 1 | P93: 1 | R93: 0 | S93: Classification | T93: Spatio-temporal | U93: ODX;k-means | V93: Trip-chaining algorithm;Clustering | W93: 1 | X93: Gordon et al. 2013 | Y93: 1 | AA93: Silhouette score | AC93: Transportation
A94: Lei, Da; Chen, Xuewu; Cheng, Long; Zhang, Lin; Wang, Pengfei; Wang, Kailai | B94: Transp. Res. Pt. C-Emerg. Technol. | C94: SEP | D94: 2021 | E94: =VLOOKUP(default_1!F141,Hoja1!$AD$1:$AE$176,2,FALSE) -> 48 | F94: 10.1016/j.trc.2021.103307 | G94: P094 | H94: Multimodal | I94: Bus;Subway | J94: 52000000 | K94: 31 | L94: 2020 | M94: Nanjing, China | N94: Open-Closed | O94: 1 | P94: 1 | R94: 0 | S94: Origin-Destination | T94: Trip chain | U94: Trip-chaining algorithm | V94: Trip-chaining algorithm | W94: 1 | X94: Lempel–Ziv entropy estimator | Y94: 0 | AA94: entropy;accuracy;log likelihood ratios;R² | AC94: Transportation
A95: Liu, Lumei; Kong, Hui; Liu, Tianliang; Ma, Xiaolei | B95: J. Transp. Eng. Pt A-Syst. | C95: MAY 1 | D95: 2022 | E95: =VLOOKUP(default_1!F5,Hoja1!$AD$1:$AE$176,2,FALSE) -> 3 | F95: 10.1061/JTEPBS.0000663 | G95: P095 | H95: Bus | J95: 103000000 | K95: 5 | L95: 2018 | M95: Beijing, China | N95: Closed | O95: 0 | P95: 1 | Q95: Web mapping service;Social/Demographic/Economic;Social/Demographic/Economic;POI | R95: 0 | S95: Pattern analysis | T95: Multimodal | U95: Binomial logit model | V95: Regression | W95: 0 | Y95: 1 | Z95: housing price;population density;land-use index | AA95: R² | AB95: ArcGIS | AC95: Transportation
A96: Tang, Tianli; Fonzone, Achille; Liu, Ronghui; Choudhury, Charisma | B96: Sust. Cities Soc. | C96: OCT | D96: 2021 | E96: =VLOOKUP(default_1!F136,Hoja1!$AD$1:$AE$176,2,FALSE) -> 6 | F96: 10.1016/j.scs.2021.103111 | G96: P096 | H96: Bus | J96: 2917272 | K96: 32 | L96: 2016 | M96: Changsha, China | N96: Open | O96: 1 | P96: 1 | R96: 0 | S96: Demand forecasting | T96: Spatio-temporal | U96: Fully connected network;Recurrent neural networks;Long-short term memory neural network | V96: Deep learning;Deep learning;Deep learning | W96: 0 | Y96: 1 | AA96: PPV;TPR;F-Score | AB96: R | AC96: Transportation
A97: Yi, Yongju; Choi, Keechoo; Lee, Young-Jae | B97: J. Publ. Transp. | D97: 2016 | E97: =VLOOKUP(default_1!F133,Hoja1!$AD$1:$AE$176,2,FALSE) -> 11 | F97: 10.5038/2375-0901.19.4.11 | G97: P097 | H97: Bus | K97: 1 | L97: 2013 | M97: Suwon, South Korea | N97: Closed | O97: 1 | P97: 1 | R97: 0 | S97: Path planning/finding | T97: Custom routes | U97: Genetic algorithm;LSBRS Regression Model | V97: Genetic algorithm;Regression | W97: 0 | Y97: 0 | Z97: Total travel time;OnOffTime;AccelerationDeccelerationTime | AA97: R²;F-Score | AB97: Matlab | AC97: Transportation
A98: Ingvardson, Jesper Blafoss; Nielsen, Otto Anker; Raveau, Sebastian; Nielsen, Bo Friis | B98: Transp. Res. Pt. C-Emerg. Technol. | C98: MAY | D98: 2018 | E98: =VLOOKUP(default_1!F110,Hoja1!$AD$1:$AE$176,2,FALSE) -> 20 | F98: 10.1016/j.trc.2018.03.006 | G98: P098 | H98: Multimodal | I98: Bus;Subway;Train | J98: 1767858 | K98: 61 | L98: 2014 | M98: Copenhagen, Denmark | N98: Closed | O98: 0 | P98: 1 | Q98: Transit Feed | R98: 0 | S98: Performance indicators | T98: Waiting time | U98: Mixture distribution | V98: Probability techniques | W98: 1 | X98: Luethi et al. (2007). | Y98: 0 | AA98: Kolmogorov-Smirnov test statistic;AIC | AC98: Transportation
A99: Nunes, Antonio A.; Dias, Teresa Galvao; Falcao e Cunha, Joao | B99: IEEE Trans. Intell. Transp. Syst. | C99: JAN | D99: 2016 | E99: =VLOOKUP(default_1!F84,Hoja1!$AD$1:$AE$176,2,FALSE) -> 43 | F99: 10.1109/TITS.2015.2464335 | G99: P099 | H99: Bus | J99: 3000000 | K99: 30 | L99: 2010 | M99: Porto, Portugal | N99: Open | O99: 0 | P99: 1 | Q99: Network;Network;Network | R99: 0 | S99: Destination estimation | T99: Estimate alighting | U99: OD matrix | V99: OD matrix | W99: 0 | Y99: 1 | AB99: SQL | AC99: Transportation
A100: Ouyang, Qi; Lv, Yongbo; Ren, Yuan; Ma, Jihui; Li, Jing | B100: J. Adv. Transp. | D100: 2018 | E100: =VLOOKUP(default_1!F114,Hoja1!$AD$1:$AE$176,2,FALSE) -> 14 | F100: 10.1155/2018/9457486 | G100: P100 | H100: Bus | J100: 150000000 | K100: 18 | L100: 2015 | M100: Beijing, China | N100: Closed | O100: 1 | P100: 1 | R100: 0 | S100: Pattern analysis | T100: Passenger | U100: Trip reconstruction;DBSCAN | V100: Trip-chaining algorithm;Clustering | W100: 0 | Y100: 1 | AB100: Apache Spark | AC100: Transportation
...

Sheet Hoja1
P1: Algorithm type | W1: Study Area | AD1: 10.1016/j.jtrangeo.2022.103415 | AE1: 11
P2: Clustering | Q2: Clustering | R2: {=_xlfn.UNIQUE(Q2:Q334)} -> Clustering | W2: Beijing, China | X2: {=_xlfn._xlws.SORT(_xlfn.UNIQUE(W2:W177))} -> Amsterdam, Netherlands | AD2: 10.1080/23249935.2022.2028929 | AE2: 4
C3: Passenger profiling algorithm | G3: {=_xlfn._xlws.SORT(_xlfn.UNIQUE(C3:C335))} -> Accesibility Index | P3: Authors algorithm | Q3: Authors algorithm | R3: Authors algorithm | W3: Taipei City, Taiwan | X3: Beer Sheva, Israel;Kiryat Gat, Israel | AD3: 10.1016/j.jtrangeo.2021.103046 | AE3: 23
C4: Time saving algorithm | G4: Agglomerative hierarchical clustering | P4: Regression | Q4: Regression | R4: Regression | W4: Nanjing, China | X4: Beijing, China | AD4: 10.1007/s00500-022-07025-8 | AE4: 6
C5: Generalised additive mixed model | G5: alighting estimation algorithm | P5: Regression | Q5: Regression | R5: OD matrix | W5: Beijing, China | X5: Bogotá, Colombia | AD5: 10.1016/j.urbmob.2022.100035 | AE5: 2
C6: Binomial logit model | G6: alighting stop inference algorithm | P6: OD matrix | Q6: OD matrix | R6: Stochastic modeling | W6: Lisbon, Portugal | X6: Brisbane, Australia | AD6: 10.1016/j.trc.2021.103267 | AE6: 2
C7: OD matrix | G7: Anomaly detection | P7: Stochastic modeling;Clustering | Q7: Stochastic modeling | R7: Optimization | W7: Seoul, South Korea | X7: Camp de Tarragona, Spain | AD7: 10.1016/j.tra.2021.02.007 | AE7: 23
C8: Hidden Markov Model | G8: ARIMA | P8: Authors algorithm;Regression | Q8: Clustering | R8: Language model | W8: Greater Toronto and Hamilton Area, Canada | X8: Changsha, China | AD8: 10.1016/j.compenvurbsys.2020.101517 | AE8: 23
C9: k-means | G9: Authors algorithm | P9: Optimization;Optimization;Clustering | Q9: Authors algorithm | R9: Descriptive statistics | W9: Daegu, South Korea | X9: Chengdu, China | AD9: 10.1080/23249935.2022.2079755 | AE9: 2
C10: Data fusion | G10: AVL, Fare and Schedule integration model | P10: Regression | Q10: Regression | R10: Deep learning | W10: Nanjing, China | X10: Copenhagen, Denmark | AD10: 10.1177/03611981221110229 | AE10: 0
C11: Multinomial logit model | G11: Bayesian Additive Model-Gaussian Process | P11: Language model | Q11: Optimization | R11: Ranking algorithm | W11: London, UK | X11: Curitiba, Brazil | AD11: 10.1109/TITS.2020.3043021 | AE11: 14
C12: Linear programming | G12: Bayesian Hierarchical | P12: Language model;Descriptive statistics | Q12: Optimization | R12: Probability model | W12: Wuhan, China | X12: Daegu, South Korea | AD12: 10.3390/s22010017 | AE12: 5
C13: Dynamic programming | G13: Bayesian model | P13: Deep learning;Deep learning;Deep learning | Q13: Clustering | R13: Dimensionality reduction | W13: Melbourne, Australia | X13: Davangere, India | AD13: 10.1155/2022/2080552 | AE13: 4
C14: Poisson distribution | G14: Bidirectional Long short-term memory | P14: Regression;Language model;Clustering | Q14: Regression | R14: Anomaly detection | W14: Chengdu, China | X14: Denmark | AD14: 10.1177/03611981211027562 | AE14: 4
C15: Gradient boosting | G15: Binary classification | P15: Regression | Q15: Language model | R15: Classification | W15: Chengdu, China | X15: Eastern Denmark, Denmark | AD15: 10.3390/s21196574 | AE15: 20
... C37: Probability distribution functions | G37: DBSACN | P37: Regression;Regression | Q37: Regression | R37: Cluster | W37: Fuenlabrada, Spain | X37: Madrid, Spain | AD37: 10.1016/j.tra.2023.103747 | AE37: 5
C38: Naive Bayes | G38: DBSCAN | P38: Classification;Classification;Classification;Classification;Classification;Feature selection | Q38: Probability model | W38: Seoul, South Korea | X38: Melbourne, Australia | AD38: 10.3846/transport.2020.14159 | AE38: 3
C39: Probability model | G39: Decision tree | P39: Regression;Regression | Q39: Clustering | W39: South-West Scania, Sweden | X39: Montréal, Canada | AD39: 10.1061/JTEPBS.TEENG-7634 | AE39: 2
C40: DBSCAN | G40: Decision Tree diagram | P40: Game theory;Classification;Classification;Classification | Q40: Deep learning | W40: Beer Sheva, Israel;Kiryat Gat, Israel | X40: Nanjing, China | AD40: 10.1016/j.trc.2022.103790 | AE40: 6
C41: STGGA | G41: Deep learning | P41: Descriptive statistics;Clustering | Q41: Clustering | W41: Seoul, South Korea | X41: New York, USA | AD41: 10.1016/j.trc.2022.103559 | AE41: 3
C42: k-means | G42: Deep Learning of Spatiotemporal Patterns | P42: Clustering;Clustering;OD matrix | Q42: Deep learning | W42: Beijing, China | X42: Osaka, Japan | AD42: 10.1016/j.tbs.2023.100587 | AE42: 5
C43: Convolutional neural networks | G43: Densely Connected Convolutional Networks | P43: Authors algorithm;Forecasting;trip-chaining algorithm;Anomaly detection | Q43: Deep learning | W43: Santander, Spain | X43: Paris, France | AD43: 10.1109/TITS.2020.2983853 | AE43: 13
C44: Densely Connected Convolutional Networks | G44: Descriptive statistics | P44: Probability model;Regression | Q44: Clustering | W44: London, UK | X44: Porto, Portugal | AD44: 10.1177/03611981211045071 | AE44: 4
C45: Spatial cluster partitioning algorithm | G45: Direct Ridership Model | P45: Panel analysis;Clustering | Q45: Dimensionality reduction | W45: Bogotá, Colombia | X45: Qingdao, China | AD45: 10.1016/j.tbs.2023.100620 | AE45: 7
C46: Dynamic mode decomposition | G46: Dwell time model | P46: Authors algorithm | Q46: Deep learning | W46: Shenzhen, China | X46: Rennes, France | AD46: 10.1016/j.tra.2022.09.010 | AE46: 4
C47: Deep Learning of Spatiotemporal Patterns | G47: Dynamic factor model | P47: OD matrix;Classifictaion;Classifictaion | Q47: Regression | W47: Melbourne, Australia | X47: Riga, Latvia | AD47: 10.1016/j.scs.2021.103111 | AE47: 17
C48: Multinomial logit | G48: Dynamic Genetic Algorithm | P48: Classification | Q48: OD matrix | W48: Seoul, South Korea | X48: Rotterdam, Netherlands | AD48: 10.1080/23249935.2021.2005180 | AE48: 7
C49: OD analysis | G49: Dynamic mode decomposition | P49: Clustering | Q49: Optimization | W49: Shenzhen, China | X49: Santander, Spain | AD49: 10.1016/j.cities.2021.103139 | AE49: 123
... C76: Logistic Regression | G76: GWNBR | P76: Regression;Regression;Clustering | Q76: Classification | W76: Shanghai, China | X76: Zhuhai, China | AD76: 10.1016/j.trc.2021.103467 | AE76: 15
C77: XGBoost | G77: GWR | P77: Classification;Regression | Q77: Descriptive statistics | W77: Nanjing, China | AD77: 10.1080/21680566.2023.2226824 | AE77: 0
C78: Accesibility Index | G78: Hamming algorithm | P78: trip-chaining algorithm;Descriptive statistics | Q78: Clustering | W78: São Paulo, Brazil | AD78: 10.1016/j.trc.2021.103307 | AE78: 11
C79: Jenks’ Natural Breaks | G79: HDDC | P79: Time series analysis;Regression;Regression | Q79: Clustering | W79: Nanjing, China | AD79: 10.1186/s12544-021-00488-0 | AE79: 48
C80: k-means++ | G80: Hidden Markov Model | P80: Clustering;Clustering | Q80: Clustering | W80: Beijing, China | AD80: 10.3390/ijerph18052711 | AE80: 8
C81: group mobility correlation | G81: Hierarchical mixture model | P81: Neural networks;Deep learning | Q81: OD matrix | W81: South East Queensland, Australia | AD81: 10.1016/j.jtrangeo.2021.103242 | AE81: 15
C82: individual correlation | G82: HIERARCHICHAL AGGLOMERATIVE CLUSTERING | P82: Clustering;Genetic algorithm | Q82: Authors algorithm | W82: Zhongshan, China | AD82: 10.1007/s12469-022-00309-0 | AE82: 0
C83: AVL, Fare and Schedule integration model | G83: Historical average time series | P83: Clustering | Q83: Forecasting | W83: Nanjing, China | AD83: 10.1061/JTEPBS.0000721 | AE83: 9
C84: Dwell time model | G84: ID-based dataset clustering | P84: OD matrix | Q84: trip-chaining algorithm | W84: Porto, Portugal | AD84: 10.1016/j.trc.2021.103210 | AE84: 10
C85: trip-chaining model | G85: IDW interpolation | P85: Descriptive statistics | Q85: Anomaly detection | W85: Nanjing, China | AD85: 10.1155/2021/9966794 | AE85: 5
C86: Anomaly detection | G86: individual correlation | P86: Deep learning | Q86: Probability model | W86: London, UK | AD86: 10.1109/ACCESS.2021.3107833 | AE86: 2
C87: Passenger to train assignment | G87: Inner-PNN-AECM | P87: Clustering;Clustering | Q87: Regression | W87: Riga, Latvia | AD87: 10.1016/j.tbs.2021.09.006 | AE87: 16
C88: Semiparametric regression | G88: IS2Fun | P88: Regression | Q88: Panel analysis | W88: London, UK | AD88: 10.1016/j.jtrangeo.2021.103075 | AE88: 17
... C98: Card ID-based analysis | G98: Lattent Dirichlet Allocation | P98: Authors algorithm;Clustering | Q98: Descriptive statistics | W98: Beijing, China | AD98: 10.1007/s11116-021-10218-z | AE98: 2
C99: Route-based analysis | G99: LDA | P99: OD matrix | Q99: Authors algorithm | W99: Beijing, China | AB99: 10.1016/j.cities.2022.103773 | AD99: 10.1016/j.cities.2022.103773 | AE99: 3
C100: Day-to-day variability model | G100: LGBM | P100: Authors algorithm | Q100: Clustering | W100: Amsterdam, Netherlands | AD100: 10.1016/j.jtrangeo.2020.102938 | AE100: 35
C101: k-means++ | G101: LightGBM | P101: Authors algorithm;Dimensionality reduction;Probability model | Q101: Regression | W101: Kansai Area, Japan | AD101: 10.1016/j.trc.2018.12.013 | AE101: 41
C102: Path size logit | G102: Linear programming | P102: Clustering;Regression;Regression | Q102: Optimization | W102: Seoul, South Korea | AD102: 10.1155/2018/2975615 | AE102: 2
C103: Broyden-Fletcher-Goldfarb-Shanno | G103: linear regression | P103: Clustering;Clustering | Q103: Gravity-based model | W103: The Hague, Netherlands | AD103: 10.18757/ejtir.2020.20.4.4084 | AE103: 8
C104: Gravity-based model | G104: Local indicators of spatial association clustering | P104: Trip destinaton model | Q104: Regression | W104: Gatineau, Canada | AD104: 10.1016/j.tranpol.2017.10.010 | AE104: 38
C105: Spatial Durbin Model | G105: Local outlier factor | P105: Time series analysis | Q105: Regression | W105: London, UK | AD105: 10.1016/j.scs.2019.101927 | AE105: 40
C106: Ordinary least squares | G106: logistic regresion | P106: Authors algorithm | Q106: Optimization | W106: Beijing, China | AD106: 10.3141/2652-06 | AE106: 12
C107: Lagrange Multiplier | G107: Logistic regression | P107: Clustering | Q107: Regression | W107: Shenzhen, China | AD107: 10.1109/ACCESS.2019.2943598 | AE107: 13
C108: Spatial Error Model | G108: Logistic regression model | P108: Classification | Q108: Descriptive statistics | W108: South East Queensland, Australia | AD108: 10.1109/TITS.2015.2464335 | AE108: 69
C109: Descriptive statistics | G109: London Output Area Clasification | P109: Clustering;Clustering | Q109: Economical model | W109: Greater Copenhagen area, Denmark | AD109: 10.1016/j.trc.2013.06.014 | AE109: 43
C110: Lorenz Curves | G110: Long short-term memory | P110: Probability model | Q110: Economical model | W110: Copenhagen, Denmark | AD110: 10.1109/TITS.2018.2875466 | AE110: 52
C111: Gini-Indexes | G111: Long-short term memory neural network | P111: Clustering | Q111: Descriptive statistics | W111: Amsterdam, Netherlands | AD111: 10.1080/03081060.2019.1576382 | AE111: 5
... C176: Ward's algorithm | G176: ReliefF | P176: Regression | Q176: Regression | W176: Montréal, Canada | AD176: 10.1145/3232229 | AE176: 14
C177: Multinomial logit model | G177: Ridership prediction model | P177: Probability model | Q177: Authors algorithm | W177: London, UK
C178: Time discrepancy identification algorithm | G178: RNN | P178: Data augmentation;Deep learning;Deep learning | Q178: Regression
C179: Ordinary least squares | G179: Rodriguez–Laio 2014 | Q179: Regression
C180: Spatial lag | G180: Route travel time prediction model | Q180: Regression
C181: Spatial Error | G181: Route-based analysis | Q181: Regression
C182: GWR | G182: rule-based procedure | Q182: OD matrix
C183: OD matrix | G183: Self organizing map | Q183: OD matrix
C184: OD matrix | G184: Semiparametric regression | Q184: Probability model
C185: Bayesian Hierarchical | G185: SHAP | Q185: Probability model
C186: Markov chain Monte Carlo | G186: Shapley Additive Explanations | Q186: Regression
C187: Multinomial Logit | G187: Single-layer perceptron neural networks | Q187: Authors algorithm
C188: Suspect identification models | G188: SMOTE | Q188: Clustering
C189: DBSCAN | G189: Spatial cluster partitioning algorithm | Q189: OD matrix
C190: Transit tensor factorization | G190: Spatial Durbin Model | Q190: Authors algorithm
... C225: Probability model | G225: Z-score | Q225: Clustering
C226: Poisson mixture | Q226: Clustering
C227: mixture of unigrams model | Q227: Regression
C228: Multivariate regression model | Q228: Authors algorithm
C229: Data fusion | Q229: Clustering
C230: DBSCAN | Q230: Language model
C231: IS2Fun | Q231: Stochastic mode
C232: Stochastic model | Q232: OD matrix
C233: OD matrix | Q233: Clustering
C234: Clustering | Q234: Regression
C235: Multinomial logit model | Q235: Clustering
C236: Agglomerative hierarchical clustering | Q236: Dimensionality reduction
C237: PCA | Q237: Regression
... C334: PSTM | Q334: Deep learning
C335: Inner-PNN-AECM
